Workbook
Name SlicerCache_Table_1_Col_1: #N/A

Sheet Introduction
A1: Context:
A2: The Global Open Research Commons International Model Working Group (GORC-WG) has been working to create a model describing commons* attributes* so that commons* developers can compare aspects across research clouds and commons*.
A4: This is the GORC WG commons* model version* 1.1. It represents the work done by the GORC-WG culminating in V1.0 of the model endorsed by RDA in October 2023, with slight revisions. Note that additional versions* of this model, as well as implementations and applications of it, are under development, and will be released in the future.
A6: What the model is:
A7: This spreadsheet representation of the model includes a flat breakdown of the essential elements* of a commons* (from the GORC-IG definitions document, see below), categories* and subcategories* of these essential elements*, and the attributes* and features* that exist for each. Of note is the relationship between all aspects of the model as presented here: the entities of essential elements*, categories*, and subcategories*, and the characteristics (attributes* and features*) that belong to them. Subcategories* are child entities of categories*, and categories* are child entities of essential elements*. Attributes* are inherited from parent to child entities, but are not necessarily shared between sibling entities. Features* are more granular than attributes*. Categories* of essential elements* may be considered mandatory and not disjoint, in the way that any entity that is part of the essential element* must belong to a category* of the essential element and may belong to more than one category*. Subcategories* are optional and not disjoint, in the way that any entity that is part of a category* may or may not belong to a subcategory*, and belong to more than one subcategory*. Possible Key Performance Idicators* (KPIs*) and metrics* for consideration are listed in the last tab. A UML visual representation of these relationships is available in this conceptual model. In addition to the statement of the model (i.e. the name of each essential element*, category*, subcategory*, attribute*, feature*, and KPI*), there are extended descriptions, examples, consideration levels*, and a listing of the source or sources where the item originated. The model is not intended to be prescriptive or indicate how any one commons* should be structured or operate, and so the consideration level* provides a gentle guide on the priority for which aspects of the model should be considered. This does not indicate that items with "Core" consideration levels* must be implemented, but that the GORC-WG has identified them as important and therefore they should be considered by any and all commons* at any development stage*. Similarly, "Desirable" items may be less critical for all commons* to consider and may be more suited to established commons*, and "Optional" for mature commons* or commons* with specific interest in those areas of work.
A9: Any word throughout the model with an asterisk (*) has a specific definition captured in the glossary. In some cases, the same word may have different meanings depending on context, and so the same word may have an asterisk in one place and no asterisk when used in another part of the model as it means something different than our model-specific definition, especially within examples. Each essential element* in the model has its own tab. Blue coloured cells indicate categories* and their information, and purple cells indicate subcategories* and their information. Orange coloured cells indicate attributes* and their information, and yellow cells indicate features* and their information. Attributes* and features* at the top of each tab that are not within a category* or subcategory* belong to the essential element*, and are inherited by each category* and subcategory*. Attributes* and features* that belong to categories* are inherited by that category's* subcategories*. Subcategories* may also have attributes* and features*, which are not necessarily shared with sibling subcategories*. The ordering of categories*, subcategories*, attributes*, and features* within each tab is not indicative of importance.
A11: How to use the model | C11: Counts
A12: Commons* developers may use this model as a guide for what to consider as they build, maintain, and expand their commons*. Not every commons* should include every item in this model, however we encourage commons* to consider having some representation in each essential element*. Commons* developers should review and consider each attribute* and feature* and the subcategories* and categories* they belong to in each essential element*, asking themselves if each is something their commons* has at a sufficient level, has but needs to improve or expand, does not have and needs immediately, does not have and needs eventually, or doesn't need at all. Developers may consider keeping explanatory notes for themselves on their decisions for each item in the model, and revisiting them over time as part of their strategic planning process. Developers may find the list of possible KPIs and metrics helpful as a starting point to determine their own success indicators and metrics. A first edition adoption tool , based on V1.0, is available for those interested in adopting the model. Note that the access level on this sheet is set to "anyone can comment". Please do leave comments and suggestions on cells throughout the model. All parts of the model should be visible, but please contact CJ at c.joseph.woodford@gmail.com if you find you cannot see any area of the model clearly. We also have a running list of issues/considerations for future versions that address overarching ideas and potential changes. To assist with determining which components of the model to consider first, each tab has a slicer in cell 1E that allows you to select whether you view all items at once or only items of a particular consideration level* at a time. A counter at the top of each sheet will inform you of how many items you are currently viewing. The totals for each essential element are to the right for reference. | C12: Essential Element* | D12: Total items | E12: Core Considerations | F12: Desirable Considerations | G12: Optional Considerations | H12: Categories* | I12: Subcategories* | J12: Attributes* & Features
C13: Governance & Leadership* | D13: =SUM(H13:I13,J13) -> 59 | E13: =COUNTIF('Governance & Leadership'!G:G, "Core") -> 41 | F13: =COUNTIF('Governance & Leadership'!G:G, "Desirable") -> 18 | G13: =COUNTIF('Governance & Leadership'!G:G, "Optional") -> 0 | H13: 5 | I13: 6 | J13: 48
A14: Relevant Resources: | C14: Rules of Participation & Access* | D14: =SUM(H14:I14,J14) -> 15 | E14: =COUNTIF('Rules of Participation & Access'!G:G, "Core") -> 11 | F14: =COUNTIF('Rules of Participation & Access'!G:G, "Desirable") -> 4 | G14: =COUNTIF('Rules of Participation & Access'!G:G, "Optional") -> 0 | H14: 2 | I14: 8 | J14: 5
A15: Global Open Research Commons International Model, version 1.1, Model documentation | C15: Sustainability* | D15: =SUM(H15:I15,J15) -> 12 | E15: =COUNTIF(Sustainability!G:G, "Core") -> 5 | F15: =COUNTIF(Sustainability!G:G, "Desirable") -> 5 | G15: =COUNTIF(Sustainability!G:G, "Optional") -> 2 | H15: 3 | I15: 5 | J15: 4
A16: The Global Open Research Commons International Model, version 1, supporting documentation; https://zenodo.org/records/10032913 | C16: Engagement* | D16: =SUM(H16:I16,J16) -> 17 | E16: =COUNTIF(Engagement!G:G, "Core") -> 11 | F16: =COUNTIF(Engagement!G:G, "Desirable") -> 5 | G16: =COUNTIF(Engagement!G:G, "Optional") -> 1 | H16: 4 | I16: 3 | J16: 10
A17: GORC IG: Typology and Definitions : https://doi.org/10.15497/RDA00087 | C17: Human Capacity* | D17: =SUM(H17:I17,J17) -> 27 | E17: =COUNTIF('Human Capacity'!G:G, "Core") -> 22 | F17: =COUNTIF('Human Capacity'!G:G, "Desirable") -> 5 | G17: =COUNTIF('Human Capacity'!G:G, "Optional") -> 0 | H17: 5 | I17: 1 | J17: 21
A18: GORC International Model WG - Commons Model V1.0 | C18: ICT Infrastructure* | D18: =SUM(H18:I18,J18) -> 28 | E18: =COUNTIF('ICT Infrastructure'!G:G, "Core") -> 20 | F18: =COUNTIF('ICT Infrastructure'!G:G, "Desirable") -> 4 | G18: =COUNTIF('ICT Infrastructure'!G:G, "Optional") -> 4 | H18: 5 | I18: 8 | J18: 15
C19: Interoperability* | D19: =SUM(H19:I19,J19) -> 21 | E19: =COUNTIF(Interoperability!G:G, "Core") -> 9 | F19: =COUNTIF(Interoperability!G:G, "Desirable") -> 11 | G19: =COUNTIF(Interoperability!G:G, "Optional") -> 1 | H19: 3 | I19: 3 | J19: 15
C20: Standards* & Conventions* | D20: =SUM(H20:I20,J20) -> 33 | E20: =COUNTIF('Standards & Conventions'!G:G, "Core") -> 10 | F20: =COUNTIF('Standards & Conventions'!G:G, "Desirable") -> 22 | G20: =COUNTIF('Standards & Conventions'!G:G, "Optional") -> 1 | H20: 10 | I20: 2 | J20: 21
C21: Services* & Tools* | D21: =SUM(H21:I21,J21) -> 74 | E21: =COUNTIF('Services & Tools'!G:G, "Core") -> 28 | F21: =COUNTIF('Services & Tools'!G:G, "Desirable") -> 36 | G21: =COUNTIF('Services & Tools'!G:G, "Optional") -> 10 | H21: 10 | I21: 10 | J21: 54
C22: Research Objects* | D22: =SUM(H22:I22,J22) -> 6 | E22: =COUNTIF('Research Objects'!G:G, "Core") -> 6 | F22: =COUNTIF('Research Objects'!G:G, "Desirable") -> 0 | G22: =COUNTIF('Research Objects'!G:G, "Optional") -> 0 | H22: 5 | I22: 0 | J22: 1
A23: © 2024. This work is licensed under a CC BY 4.0 license. Attribute as "Commons Model V1.1, GORC IM WG, 2024" | C23: Subtotals | D23: =SUM(D13:D22) -> 292 | E23: =SUM(E13:E22) -> 163 | F23: =SUM(F13:F22) -> 110 | G23: =SUM(G13:G22) -> 19 | H23: =SUM(H13:H22) -> 52 | I23: =SUM(I13:I22) -> 46 | J23: =SUM(J13:J22) -> 194
A24: Cite as: | C24: KPIs* & metrics* | D24: 104 | E24: =COUNTIF('KPIs & Metrics'!E:E, "Core") -> 49 | F24: =COUNTIF('KPIs & Metrics'!E:E, "Desirable") -> 34 | G24: =COUNTIF('KPIs & Metrics'!E:E, "Optional") -> 21
A25: Woodford, C. J., Treloar, A., Leggott, M., Payne, K.., Jones, S., Lopez Albacete, J., Madalli, D., Genova, F., Dharmawardena, K., Chibhira, N., Åkerström, W. N., Macneil, R., Nurnberger, A., Pfeiffenberger, H., Tanifuji, M., Zhang, Q., Jones, N., Sesink, L., & Wood-Charlson, E. (2024). The Global Open Research Commons International Model, Version 1.1 (Version 1.1). Research Data Alliance. https://doi.org/10.15497/RDA00119 | C25: Total Considerations: | D25: =D23+D24 -> 396 | E25: =SUM(E23:E24) -> 212 | F25: =SUM(F23:F24) -> 144 | G25: =SUM(G23:G24) -> 40
A27: Acknowlegements and thanks are extended to all GORC-WG members, speakers, and RDA community members who provided input to and feedback on the model. In particular, we thank Corrie, B., Crawley, F., Harrower, N., Maxwell, L., Sansone, S. A. for their contributions.

Sheet Glossary
A1: Glossary | B1: As much as possible, it is preferred we make definitions more inclusive rather than exclusive. This glossary is listed alphabetically. | C1: -
A2: Term | B2: Current definition | C2: Notes / source
A3: Attribute* | B3: A standard, characteristic, functionality or point of reference from which information can be documented, or measurements or comparisons may be made. Attributes* are the top level characteristics of entities (essential elements*, categories*, subcategories*). e.g. "Metadata content" is an attribute of the category "Metadata standards" within the "Standards & Conventions" essential element*. | C3: Adapted from the GORC-WG case statement
A4: Block-based Storage* | B4: Block storage is an approach to data storage in which each storage volume acts as an individual hard drive that is configured by the storage administrator. In the block storage model, data is saved to the storage media in fixed-sized chunks called blocks. Each block is associated with a unique address, and the address is the only Metadata* assigned to each block. | C4: Adapted from https://www.techtarget.com/searchstorage/definition/block-storage,
A5: Category*, Subcategory* | B5: A grouping or classification within an essential element* of items that share attributes* and features*. Categories* may be broken down further into subcategories*. Any attributes* and features* of the essential element* to which the category* belongs are inherited by that category*, and likewise by any subcategories*. For example, in the essential element* ICT Infrastructure*, the category* "Storage Infrastructure" has two subcategories*: "Direct attached storage [...]" and "Network based storage [...]". This category* has one attribute, "Knowledge and management of storage infrastructure", that is inherited by both of its subcategories*. Likewise, ICT Infrastructure* itself has two attributes, "Infrastructure is designed to scale with changing volume, complexity, and velocity of projects and expectations" and "A review and update of ICT infrastructure* happens on a regular basis". Both of these attributes, as well as the features in the latter, are inherited by the "Storage Infrastructure" category and its subcategories, such that any direct-attached, network-based, or other storage infrastructure a commons* has should have considerations for changing needs, be reviewed and updated, and have method(s) for accumulating and maintaining knowledge about them, such as a wiki. | C5: Task Group 5 Phase 2 Evaluation (May - September 2023), https://joeyhoer.com/attributes-vs-categories-6f3c9bab
A6: Collection* (of Research Objects*) | B6: A combination or bundle of Research Objects* that are of the same kind or different kinds that share a relationship, is treated as a digital object* which may bear a PID*, and consists of a finite number of digital object* identifiers and Metadata* associated with each referenced identifier. | C6: Research Data collections WG Recommendations, CURE-FAIR WG (10 things for curating reproducible and FAIR research), Speaker series (NII), Task Group 3 Phase 1 Evaluation (October 2022 - April 2023)
A7: Commons*, Research commons* | B7: A trusted ecosystem that provides seamless access to high quality, interoperable research outputs and Services*. While commons* may be focused on a specific discipline or geographic region, they should have the intent to be part of the global data ecosystem. The scope of this and related documents is intentionally restricted to digital information, and intentionally does not include the instruments that generate the data that may be made available through the commons*. | C7: Adapted from the GORC-IG typology
A8: Community*, Research commons community* or commons community* | B8: All human individuals and entities that could be considered stakeholders*, Users*, Providers*, Members* and intermediaries of the commons* (i.e. those who do not interact directly with the commons, but use information about or provided by the commons, e.g. policy makers, journals, funders) in the past, present, and future as well as all research communities that the research commons* is a part of in a regional, national, and global context. Depending on the structure of the commons*, may include funding and government bodies as well as related commercial entities, such as through related Services* or associated with related research communities. | C8: GORC-WG Phase 1 Evaluation (October 2022 - April 2023)
A9: Consideration Level* | B9: Consideration levels* indicate the priority or importance with which each item in the model should be considered. There are three levels, with 'Core' indicating items that are critical to consider for a commons* at any development stage* and in any discipline, 'Desirable' indicating items that should be considered by established commons* or those looking to expand, and 'Optional' indicating items that may be considered by commons* with particular interest in those areas. | C9: GORC-WG Phase 2 Evaluation (May - September 2023)
A10: Data space* | B10: Any digital location that incentivises the sharing of data and/or facilitates the use of data across any research discipline or field. Includes research data commons*, data Repositories*, data portals, research commons*, and any interlinked Service* such as HPC infrastructures or VRE platforms*. Note that data space*s may also be physical locations, but we are not concerned with physical data space*s in this model. | C10: Adapted from EOSC Monitoring Framework
A11: Development Stage* | B11: The stage that a commons* is in regarding its development. This speaks to the main goal of the commons* at present, spanning: Initial [getting building blocks in place, before development or implementation of external-facing services*], Developing [main foundation of commons* is in place and the commons* is starting to develop, trial, and open external facing services* and tools*], Established [recognized in research community with core services in place], Expanding [core services are well in place, looking to bolster current services and/or expand offerings/audience]. Note that "Established" may be the end goal for a commons*, as "Expanding" is specifically for growing beyond the original mission of the commons*. Additionally, development stage* is not the same as commons* age or maturity, since the time spent in any one stage will be context dependent, however development stage* and age may be correlated. Used in KPIs* & Metrics* as a guideline on when during their development a commons* may wish to consider particular measurements and indicators. | C11: Phase 2 Review (Literature Analysis, November 2022 - June 2023), adpated from Research Data Management Support Services by Libraries - A LIBER/ADBU Toolkit (https://zenodo.org/record/8101818)
A12: Digital object* | B12: A digital object* (DO*) is represented by a bitstream, is referenced and identified by a persistent identifier and has properties that are described by Metadata*. | C12: Adapted from RDA data foundation and terminology - DFT: Results RFC
... A22: Interoperability* (essential element*) | B22: The ability of Research Objects* or Tools* from different resources to integrate or work together with minimal effort. e.g. A research data file can be used by two different commons* HPC infrastructure. | C22: Adapted from the GORC-IG typology, from Wilkinson et al. 2016, essential element*
B23: Legal Interoperability*: A category* of Interoperability*. The ability to combine Research Objects* from multiple sources without conflicts among restrictions imposed by the license of each Research Object*; Research Objects* should be reusable. Covers the broad environment of laws, policies, procedures, and cooperations agreements needed to allow the seamless exchange of information and reusability of Research Objects* between difference individuals, organizations, and across jurisdictions. | C23: (EOSC FAIR-WG) EOSC Interoperability* framework - Publications Office of the EU [2021, https://data.europa.eu/doi/10.2777/620649]
B24: Organizational Interoperability*, Pragmatic Interoperability*: A category* of Interoperability*. How organizations align their business processes, responsibilities and expectations to achieve commonly agreed and mutually beneficial goals; meeting the requirements of the shared commons community* by making Services* available, easily identifiable, accessible, and community* member-focused Considerations for Interoperability* with other commons*, repos, public research institutions, private research institutions, and commercial entities, among other entities in the community*, are included. | C24: Adapted from (EOSC FAIR-WG) EOSC Interoperability* framework - Publications Office of the EU [2021, https://data.europa.eu/doi/10.2777/620649]
B25: Semantic Interoperability*: the ability of computer systems to transmit information with unambiguous, shared meaning; a requirement to enable machine computable logic, inference, knowledge discovery, and Research Object* federation between information systems; what is sent is what is understood by both humans and machines. | C25: (EOSC FAIR-WG) EOSC Interoperability* framework - Publications Office of the EU [2021, https://data.europa.eu/doi/10.2777/620649]
B26: Technical Interoperability*: the ability of different information technology systems and software applications to communicate and exchange Research Objects*, and specifically to accept Research Objects* from each other and perform a given task in an appropriate and satisfactory manner without the need for extra operator intervention. | C26: (EOSC FAIR-WG) EOSC Interoperability* framework - Publications Office of the EU [2021, https://data.europa.eu/doi/10.2777/620649]
A27: KPI*, Key Performance Indicator | B27: Qualitative and quantitative measures used within and by the commons* to measure the uptake, engagement or use of a category*, subcategory*, Attribute* or feature*. KPIs* are often used to measure success, adoption, and use specifically. | C27: Adapted from the GORC-WG case statement
A28: Machine Actionable* | B28: Machine Actionable* means that a formal statement is syntactically and semantically specified enabling computing systems to carry out automatic processing. | C28: (EOSC FAIR-WG) A Persistent Identifier (PID*) policy for the European Open Science Cloud (EOSC) - Publications Office of the EU [2020, https://data.europa.eu/doi/10.2777/926037]
A29: Members* | B29: A human individual or entity, such as research institutions, that participate in the commons*. Participation may include but is not limited to being Providers*, granting access or creating pathways for Users* to engage with the commons*, and participating in the governance* structure of the commons*. Being a member of a commons* is the highest level of interaction without being an employee or hosting organization. Eg. a member is participating on the Data Management Plan task group of the commons*. | C29: GORC-WG Phase 1 Evaluation (October 2022 - April 2023)
A30: Metadata* | B30: Information about the Research Object*, Service*, Tool*, or other entity being described. Often stated as "data about data". Metadata* typically contains descriptive, contextual and Provenance* assertions about the properties of a digital object*. | C30: GORC-WG Phase 1 Evaluation (October 2022 - April 2023)
A31: Metric* | B31: A metric* is a quantifiable measure that is used to track and assess the evolution or performance of specific processes | C31: A Set of Common Service Quality Assurance Baseline Criteria for Research Projects [2022] https://digital.csic.es/handle/10261/214441
A32: Object based Storage* | B32: A stored object is a logical collection* of bytes that are of variable size and can be used to store entire data structures, such as files, database tables, medical images, or multimedia. Object-based storage offers the efficiency of block storage and the control of file storage. | C32: Adapted from https://ieeexplore.ieee.org/document/1222722#citations
A33: PID*, Persistent Identifier* | B33: A persistent identifier* is a long-lasting ID represented by a string that uniquely identifies a digital object* and that is intended to be persistently resolved to meaningful state information about the identified digital object. A PID may also be defined by it's characteristics, i.e. that PIDs: are uniquely identifying a specific Digital Object*; in general consist of a name space indicator (prefix) and a local identifier (suffix); are actionable on the web, by extending it to a fully defined URI, if required; can be persistently resolved to state information and/or a landing page; are associated with a persistent resolution system; are issued and managed by a clearly specified registration authority. | C33: Adapted from Persistent Identifiers: Consolidated Assertions, from the RDA Data Fabric IG and RDA Data foundation and Terminology WG
A34: PID* record* | B34: A PID* record* or kernel is a minimal set of information about the digital object* communicated between machines. At minimum, it contains the pair between the PID* and the landing page or access URL for the Metadata*. | C34: Adapted from Persistent Identifiers: Consolidated Assertions, from the RDA Data Fabric IG and RDA Data foundation and Terminology WG D2.4 2nd report on FAIR requirements for persistence and Interoperability [2020, FAIRsFAIR]
A35: Platform*, Research Platform* | B35: Research platforms and Services* (virtual science labs, VREs, science gateways) instantiate a collection* of Research Software* source code, including large software frameworks, discipline-specific Tools*, Services*, and glue code, and are deployed to support both the research workflows and the communities of practise engaged in collaborative research. Capabilities include: DAM, processing and visualisation, storage and preservation, sharing and discovery. EX: FRDR, Syzygy, PIMS, CWRC | C35: Research Software* Current State Assessment [2021] (https://alliancecan.ca/sites/default/files/2022-03/rs_current_state_report_1.pdf)
A36: Provenance* | B36: Any and all information regarding the creation, curation, maintenance, context, rights and responsibility for a Research Object*. | C36: Influenced by https://ckaestne.medium.com/versioning*-Provenance*-and-reproducibility-in-production-machine-learning-355c48665005
A37: Providers* | B37: An individual or entity, human or machine, that provides Services*, Tools*, and/or Research Objects* to the commons* or to Users* on behalf of the commons*. Providers* may also be Users* and Members*. Ex. a Provider* deposits a dataset into the commons*' Repository*, a third-party company provides digitization Services* for commons* Users*
A38: Publishers* | B38: An entity, human or machine, that prepares and issues a Research Object* for distribution or otherwise makes the Research Object* public, so that it may be shared and discovered. This includes but is not limited to peer-review and open access journals, data Repositories*, government bodies, pre-print Repositories*, blogs, and digital spaces owned and operated by research institutions and organizations, such as websites and news columns. Specific examples include websites such as Zenodo, an institutional or discipline Repository* such as GBIF, or a software Repository* such as Github.
A39: Publication* | B39: A text based scholarly Publication* or publishing channel that contains results of research. CRISs typically record Metadata* about scholarly Publications* from the scope of the CRIS (institutional CRIS for the institution, funder CRIS for the funding it distributed, etc.) in the context of the research projects, infrastructure, funding, organization units and authors/contributors. This entity typically represents the granularity level of a single published item for which attribution information is attached (usually in the form of a list of authors and contributors). This entity is also used to represent publishing channels and sources: journals and book series (incl. continuing conference proceedings series). | C39: OpenAIRE Guidelines [2022] (https://guidelines.openaire.eu/en/latest/index.html) Publication* Metadata* in CERIF: Inspiration by FRBR (https://doi.org/10.1016/j.procs.2014.06.008)
A40: Repository*, Repositories*, Repo*, Repos* | B40: A system for Research Object* storage and management. Repositories* may aggregate Research Objects* from other Repositories*, and may be a part of or are harvested by commons*. Repositories* typically do not have Services* or Tools* beyond essential storage and management. | C40: Adapted from RDA data foundation and terminology - DFT: Results RFC
A41: Research Compendium* | B41: A bundle of all the research artifacts used and necessary to support a research claim, such that the claim is completely reproducible using only what is provided or referenced in the research compendium*. | C41: CURE-FAIR WG, 10 things for curating reproducible and FAIR research
A42: Research Data* | B42: An assembly of data that is identifiable and has the potential to be curated or published by a single actor and is the result or focus of research activities. Research data can digitally represent a group of observations, a data product from a specific version* of a processing algorithm based on observations, output of numerical model(s), or outcomes of laboratory experiments. Research data serve as the object(s) of an investigation, whether scientific, scholarly, literary or artistic, and are used to create more or other research data. | C42: Global Community Guidelines for Documenting, Sharing, and Reusing Quality Information of Individual Digital Datasets https://datascience.codata.org/articles/10.5334/dsj-2022-008/ Canadian Tri-Agency (https://science.gc.ca/eic/site/063.nsf/eng/h_97609.html#1a), Random Encounters (CANLIB discussion)
A43: Research Object* (essential element*), Research Artefact* | B43: Any input to, or output of, any and all stages of the research process. For this version of the model (V1.0), we only consider Research Objects* that are Digital Objects*, as we have confined the model to digital and e-infrastructures. | C43: Adapted from the GORC-IG typology, essential element*
A44: Research Software* | B44: Source code files, algorithms, scripts, computational workflows, and executables that were created during the research process or for a research purpose. Software components (e.g. operating systems, libraries, dependencies, packages, scripts, etc.) that are used for research but were not created during or with a clear research intent should be considered software in research and not Research Software*. | C44: Amsterdam Declaration on Funding Research Software* Sustainability [V0.3, 2023] (https://zenodo.org/record/7330542#.Y5ts83bMJdg)
A45: Rules of Participation & Access* (RoP) (essential element*) | B45: A set of policies defining a minimal set of rights, obligations, and accountability governing the activities of those participating in the commons*. | C45: Adapted from the GORC-IG typology, from EOSC, essential element*
A46: Semantic Artifacts, Semantic Objects* | B46: Semantic Objects* are a named grouping of descriptive elements that sufficiently describe a distinct identity. Semantic Objects* may be in the form of documentation, Research Software*, or research data*. They may also be referred to as Semantic Artefacts*, defined as groups of entities with unique identifiers where entities include subjects, predicates, and objects that can be linked together to form a network that describes a dataset. In this model, Semantic Objects*/Artefacts are not considered as collections, since collections are comprised of Research Objects* and not entities. | C46: Adapted from D2.1 Report on fair requirements for persistence and Interoperability [2019, FAIRsFAIR]
A47: Service* (essential element*) | B47: Any commons* element that can be invoked by Users* to perform some action on their behalf. | C47: Adapted from the GORC-IG typology, from IVOA, essential element*
B48: Data Service*: any Service* that acts on at least one component of the ‘holy trinity of data management’: the bit sequence, the Metadata* and the PID* of a digital object*. This includes Services* that bind these components together (e.g. associating Metadata* with a bit sequence), Services* that deliver data to the User*, Services* that automatically analyze or transform data, Services* that aggregate and index Metadata*, Services* that store or replicate data, etc | C48: M2.7: Assessment report on 'FAIRness of Services*' [2020, FAIRsFAIR] (https://doi.org/10.5281/zenodo.5470375)
A49: Stakeholder* | B49: Any human individual or entity that represent themself or a non-human (animal, plant, land, resource, or technology) entity or group that is associated with, is a member of, participates in, provides to, or uses the commons* past, present, and future. e.g. Producers, Users*, and re-Users* of research data; Funders of research infrastructures and the production of research data; Policy developers for research data management e.g. “Core”: governance* bodies and committees, Members*, secretariat; Funders and influencers: national ministries and agencies, public science funders and councils, intergovernmental bodies and organizations, foundations and charities, industry; Users*, data controbiters, data Publishers*: individuals and organizations such as intergovernmental bodies and others, and projects; Discipline or otherwise related informatics: other infrastructures, IT departments at related institutions, standardization bodies, projects, and other initiatives | C49: Briefing Paper on EOSC: Federating Research Infrastructures in Europe for Fair Access to Data [2022] (https://www.scienceeurope.org/our-resources/briefing-paper-on-eosc/) Twenty-Year Review of GBIF (https://doi.org/10.35035/ctzm-hz97)
A50: Standards & Conventions*, Standards* (essential element*) | B50: A standard* is a repeatable, harmonized, agreed and documented way of doing something. They are typically certified by an official endorsing body (e.g. ISO) and are formally recognized. A convention* is similar in that they define a way in which something is usually done, but will typically be informal and specific to the internal operations of the commons*. Conventions*, as used in this model, are considered at least repeatable and agreed upon within the commons*, if not also documented and harmonized. | C50: Adapted from the GORC-IG typology, from IRENA, essential element*, developed in Phase 2 Evaluation (May - September 2023)
A51: Sustainability* (essential element*) | B51: Models and agreements made on how to fund or resource activities in a way that can be sustained over the long term. | C51: Adapted from the GORC-IG typology, essential element*
A52: Tool* (essential element*) | B52: Any commons* element that enables Users* to perform one or more operations, typically on data with data as the output. | C52: Adapted from the GORC-IG typology, essential element*
A53: Users* | B53: Individuals, humans or machines, that use a Service* of the commons* or are the recipient or beneficiary of a Service*. Users* may also be Members* and Providers*, but in this role are not required to contribute anything to the commons*. E.x. a User* types keywords into a search bar to find relevant datasets
A54: Version*, Versioning* | B54: The saved state of a Research Object*, process, or configuration that is unique from previous states. Versioning* includes revisions (successive) and variants (parallel), as well as dedicated releases. Types of versioning* include storing modified copies in their entirety, storing deltas between states, offsets in append-only Research Objects*, versioning* individual records, and versioning* pipelines to recreate derived Research Objects*. | C54: Influenced by https://ckaestne.medium.com/versioning-Provenance-and-reproducibility-in-production-machine-learning-355c48665005

Sheet Governance & Leadership
A1: Essential Element*: Governance & Leadership* | C1: Items in active view: | D1: =SUBTOTAL(103, G3:G61) -> 59 | E1: - | F1: - | G1: - | H1: -
A2: Category* | B2: Subcategory* | C2: Attribute* | D2: Feature* | E2: Extended Description | F2: Examples | G2: Consideration Level* | H2: Primary Source(s)
A3: Commons* intent and definition | E3: - | F3: - | G3: Core | H3: Phase 2 Review (Literature Analysis, November 2022 - June 2023)
C4: Statement of current commons* nature, mandate, and value proposition. Reference to any prior mandates and how the commons* has changed over time. | E4: - | F4: e.g. type of authority (formally government mandated or informally community* driven), scope of Services* e.g. the commons* carefully considers actions to avoid scope creep, i.e. unplanned or unmanaged growth, that could cause issues with resources or impede on other organizations’ area of work. | G4: Core | H4: Phase 1 Workshop (co-located with RDA P20, 24 March 2023) Twenty-Year Review of GBIF (https://doi.org/10.35035/ctzm-hz97)
C5: Identification and definition of the commons* community* and stakeholders, how their needs intersect with the commons*, and how the commons* engages with the community* to fulfill their needs | E5: - | F5: e.g. through environmental scanning (landscape reviews, etc.) to find needs, wants, aspirations of stakeholders ; competitive advantage (i,e, gaps in current Services*), community*-aligned policies and operations; e.g. Identification and communication of value chains at varying levels (e.g. biosphere > biodiversity > impact on society, data > information > knowledge > impact on a sector of application ) and usage of “success stories”, where value chains and quantitative metrics* are combined to illustrate narratives to specific stakeholders (e.g. # of citations for science funder, monetary value for agency of economic development) e.g. Different value propositions for different stakeholder groups (e.g. researchers, citizen scientists, industry and enterprises, universities, standard development organizations, policy making organizations, specialized Service* Providers*, research funding agencies, research infrastructure and e-Infrastructure) e.g.There is a statement, listing, or set of collections* that illustrates the higher-level subject areas/disciplines that the commons** covers or includes, as well as cross-disciplinary domain | G5: Core | H5: The four pillars of governance best practice for New Zealand Directors (https://www.iod.org.nz/resources-and-insights/4-pillars-landing-page/#) Twenty-Year Review of GBIF (https://doi.org/10.35035/ctzm-hz97) D5.1 FAIRsFAIR Communication, Marketing and Engagement Plan [2019. FAIRsFAIR] (https://doi.org/10.5281/zenodo.6656060) RDA Fairsharing WG
C6: Development of mission and vision statements and making them accessible publicly | E6: A vision statement is a statement of an organization’s overarching aspirations of what it hopes to achieve or to become. A mission statement describes what the organization needs to do now to achieve the vision. Mission and vision statements support each other, and neither list specific goals or actions. The mission statement however, is more actionable and leads to the creation of strategic goals. | F6: EX. The vision of the ISC is science as a global public good. The mission of the ISC is to act as the global voice of and for science. The strategic goals are that the ISC: acts as the legitimate and effective voice of science all over the world, particularly to the many components of the international policy community* ; serves as a thought leader in the evolution of science and science systems ; stimulates and support the coordination of international scientific endeavours on major issues of global concern ; promotes the appropriate and effective use of science in policy making, societal decision making and diplomacy, including by increasing trust in science and by defending freedom and responsibility in science ; acts with assurance and professionalism on behalf of a diverse, strong, global constituency of scientists. Source: (https://council.science/about-us/) | G6: Core | H6: GORC-IG Typology (https://docs.google.com/document/d/19222GItDg3tcrLsDUqg9Z7GLwPELaS-XHEbN6796Tvc/edit?usp=sharing)
C7: Development of values and/or guidance principles | E7: The values statement defines what the organization believes in and how people in the organization are expected to behave. Principles may be defined for overarching conditions (e.g ethics and integrity, inclusiveness, respect to scientific freedom etc) and for guiding the mission/objectives of the commons* (openness, excellence, quality, impact etc). | F7: EX: In fulfilling its role, the values that the Council will uphold in its work, its governance* and its partnerships include: • Excellence and professionalism ; • Inclusivity and diversity ; • Transparency and integrity ;• Innovation and sustainability (https://council.science/wp-content/uploads/2020/06/ISC-Statutes-and-Rules-of-Procedure_02.2021.pdf) e.g. openness, transparency, honesty, equity, fair competition, objectivity, democratic participation | G7: Core | H7: GORC-IG Typology (https://docs.google.com/document/d/19222GItDg3tcrLsDUqg9Z7GLwPELaS-XHEbN6796Tvc/edit?usp=sharing)
A8: Commons* Strategic Planning | E8: i.e. including governance* structure, stakeholder* strategy, sustainable operational strategy, and a strategy for the future | F8: - | G8: Core | H8: Task Group 1 Phase 1 Evaluation (October 2022 - April 2023)
C9: Development of strategy | E9: addressing how it responds to customer segments and delivers value propositions and meet its mandate etc. | F9: - | G9: Core | H9: Phase 2 Evaluation (May - September 2023)
D10: Strategic planning influences and approaches | E10: i.e. non-research or organization specific influences on how strategy is created or how strategic planning should progress. This speaks to strategic planning frameworks and methods. | F10: e.g. Consideration for shareholder vs stakeholder prioritization in strategies and planning, where a hybridization is possible e.g. Balance between performance and conformance in setting strategic goals, expectations, and metrics* (Performance here means: setting and monitoring strategy, strategic risk management, long-term attraction and allocation of human, physical, and financial matters ; Conformance means controls, reporting, compliance) | G10: Desirable | H10: The four pillars of governance best practice for New Zealand Directors (https://www.iod.org.nz/resources-and-insights/4-pillars-landing-page/#)
D11: Development of relevant roadmaps | E11: - | F11: e.g. investment roadmap, platform* roadmap, technology roadmap | G11: Core | H11: Phase 1 Workshop (co-located with RDA P20, 24 March 2023)
D12: Development of organizational performance and capability metrics* | E12: - | F12: e.g. Metrics* for 6 capitals: financial, manufactured, intellectual, human, social, relationship, natural e.g. Organizational design and capability/practise maturity, including both quantitative and qualitative KPIs*, goals, and milestones | G12: Desirable | H12: GORC-IG Typology (https://docs.google.com/document/d/19222GItDg3tcrLsDUqg9Z7GLwPELaS-XHEbN6796Tvc/edit?usp=sharing)
D13: A monitoring organizational design or organizational performance system to gather qualitative and quantitative metrics* | E13: - | F13: e.g. such as a task group or other governance* body that designs, decides on, gathers data for, and presents KPIs* | G13: Desirable | H13: Speaker Series - EOSC: https://eosc.eu/sites/default/files/2022-05/Monitoring%20Framework.pdf, from https://eosc.eu/key-performance-indicators-KPIs-monitoring
D14: Regular strategic review and alignment exercises | E14: i.e. including evaluation of KPIs*, purpose and direction of the commons*, and all governance* aspects; policy feedback cycles; identification of strategic elements; linkage to international landscape / ecosystem through needs assessments, Considerations for growth, e.g. more rigorous separation of governance* and management, changes to strategic planning, Assess environment (landscape review) including: political, economic, social, technological, environmental, legal, conduct competitor/market analysis | F14: e.g. through internal audits e.g. annual reviews as well as long-term reviews, such as decadal reviews | G14: Core | H14: Task Group 1 Phase 1 Evaluation (October 2022 - April 2023) The four pillars of governance best practice for New Zealand Directors (https://www.iod.org.nz/resources-and-insights/4-pillars-landing-page/#)
C15: Development and implementation of community* relations | E15: i.e. Engagement* with stakeholders on matters that affect them and Shareholder relations (if applicable | F15: e.g. Indigenous community* partnerships c.f. constitution, commercial relationship building | G15: Core | H15: GORC-IG Typology (https://docs.google.com/document/d/19222GItDg3tcrLsDUqg9Z7GLwPELaS-XHEbN6796Tvc/edit?usp=sharing) The four pillars of governance best practice for New Zealand Directors (https://www.iod.org.nz/resources-and-insights/4-pillars-landing-page/#)
B16: Funding and Resourcing Frameworks | E16: i.e. ensuring ability to function and continue operations | F16: - | G16: Core | H16: NIST Research Data Framework (RDaF) V1.5 (https://nvlpubs.nist.gov/nistpubs/SpecialPublications/NIST.SP.1500-18r1.pdf)
C17: Identification of the financial and resource requirements for commons* activities | E17: - | F17: - | G17: Core | H17: NIST Research Data Framework (RDaF) V1.5 (https://nvlpubs.nist.gov/nistpubs/SpecialPublications/NIST.SP.1500-18r1.pdf)
D18: Environmental considerations | E18: i.e. cost of implementing or not implementing environmentally conscious or damaging practises and infrastructure | F18: e.g. climate change and carbon footprint, environmental protection, biodiversity, pollution and resource depletion, water use, waste management, energy, sustainable procurement | G18: Desirable | H18: NIST Research Data Framework (RDaF) V1.5 (https://nvlpubs.nist.gov/nistpubs/SpecialPublications/NIST.SP.1500-18r1.pdf)
D19: Social considerations | E19: i.e. cost of implementing appropriate social obligations for Internal Personnel* and the commons* community* | F19: e.g. health and safety, labour standards*, human rights, fair trade, harassment/discrimination, people management, diversity and equality, supply chain management, privacy and ethics, consumer responsibility | G19: Desirable | H19: NIST Research Data Framework (RDaF) V1.5 (https://nvlpubs.nist.gov/nistpubs/SpecialPublications/NIST.SP.1500-18r1.pdf)
D20: Governance* considerations | E20: i.e. cost of governance* operations | F20: e.g. board composition and diversity, leadership, remuneration, shareholder rights, ethics, whistle blowing, disclosure and transparency, risk management, anti-bribery and corruption, stakeholder engagement* | G20: Desirable | H20: NIST Research Data Framework (RDaF) V1.5 (https://nvlpubs.nist.gov/nistpubs/SpecialPublications/NIST.SP.1500-18r1.pdf)
C21: Demonstration of added value | E21: Includes assessing cost (financial or otherwise) by stage or area of focus within the commons* and downstream costs. | F21: e.g. Economic impact of reuse of ROs (feeds into value statement of commons*), open source software and Tool* development and use e.g. Cost-benefit analysis for Sustainability* options | G21: Desirable | H21: NIST Research Data Framework (RDaF) V1.5 (https://nvlpubs.nist.gov/nistpubs/SpecialPublications/NIST.SP.1500-18r1.pdf)
B22: Risk Management Frameworks | E22: May have different frameworks for different types and impacts of risk, such as for governance*, management, technical and operational, related to Sustainability* etc. | F22: contingency plans to ensure Research Objects* are available and maintained during and after unforeseen events | G22: Core | H22: GORC-IG Typology (https://docs.google.com/document/d/19222GItDg3tcrLsDUqg9Z7GLwPELaS-XHEbN6796Tvc/edit?usp=sharing)
C23: Identification of risks and issues | E23: - | F23: e.g. through considerations for crises (economic (strike, market crash), financial (unexpected loss of finances), informational (cyber-attacks or leaks), physical (loss or breakdown of equipment), health (pandemics), human resources (loss of personnel), reputation, as a result of human acts (sabotage, terrorism, workplace violence), natural disasters) e.g. risk perception and literal risk | G23: Core | H23: Task Group 1 Phase 1 Evaluation (October 2022 - April 2023)
C24: Development of risk management frameworks | E24: If a full framework is untenable, a risk strategy with key considerations may suffice. The developmet of risk management frameworks considers the balance between the liklihood of the risk and the impact. | F24: - | G24: Core | H24: GORC-IG Typology (https://docs.google.com/document/d/19222GItDg3tcrLsDUqg9Z7GLwPELaS-XHEbN6796Tvc/edit?usp=sharing)
D25: Business continuity planning | E25: i.e. including how to manage identified risks, and disaster recovery plan (i.e. covering health and safety of workers, alternate premises, alternative technology platforms, key personnel strategy, plans that include customers or contractors on site, financial management including payroll systems, media management plan, infrastructure safety, essential Services*, communications, management of data and key documents) | F25: - | G25: Core | H25: The four pillars of governance best practice for New Zealand Directors (https://www.iod.org.nz/resources-and-insights/4-pillars-landing-page/#)
D26: Technology and information governance* planning | E26: i.e. considerations for cybersecurity, data protection and managing privacy breach risk, prevention of information leakage, malware risk, loss of information/data, management of capital-intensive projects, avoiding obsolescence and opportunity costs, data breach reporting, compliance with privacy and IP laws, | F26: - | G26: Core | H26: The four pillars of governance best practice for New Zealand Directors (https://www.iod.org.nz/resources-and-insights/4-pillars-landing-page/#)
D27: Health and safety governance* planning | E27: i.e. considerations for risk culture, setting policies, mental health and wellbeing | F27: - | G27: Core | H27: The four pillars of governance best practice for New Zealand Directors (https://www.iod.org.nz/resources-and-insights/4-pillars-landing-page/#)
D28: Human rights risk identification and management | E28: i.e. considering safe working conditions, fair wages, protection from forced labour, freedom from harassment and discrimination through protection, respect, remedies to breaches | F28: - | G28: Core | H28: The four pillars of governance best practice for New Zealand Directors (https://www.iod.org.nz/resources-and-insights/4-pillars-landing-page/#)
C29: Implementation and operationalization of risk management frameworks | E29: - | F29: e.g. Insurance and indemnities, including a set claims process | G29: Core | H29: Task Group 1 Phase 1 Evaluation (October 2022 - April 2023)
B30: Policy advocacy, and recommendations | E30: Advocacy towards policy makers and other stakeholders* ( i.e. Governance and leadership* role in advocacy, aligned with mission and mandate) as well as the research community* | F30: setting or informing national policy, research discipline-specific policies | G30: Desirable | H30: Phase 1 Workshop (co-located with RDA P20, 24 March 2023)
A31: Organizational structures, designs, ways of working, and capability maturity level for the aims and context of the commons* | E31: Including a clear definition of working relationships between governance* and management | F31: - | G31: Core | H31: GORC-IG Typology (https://docs.google.com/document/d/19222GItDg3tcrLsDUqg9Z7GLwPELaS-XHEbN6796Tvc/edit?usp=sharing)
C32: Explicit decision making processes, specifying who makes decisions in what scenarios and when | E32: - | F32: - | G32: Desirable | H32: GORC-WG Case Statement: https://www.rd-alliance.org/sites/default/files/GORC%20International%20Model%20WG_%20Case%20Statement%20V4%20July%202021.pdf, National Data Services IG: https://www.rd-alliance.org/groups/national-data-Services.html
D33: Formal reporting framework | E33: i.e. reporting from Management to Governance*, Governance* reporting to funders, etc. | F33: e.g. Monitoring and reporting on Key performance indicators and trend data, Monitoring of Rules of Participation & Access* and compliance, reporting on the qualitative and quantitative compliance with the rules of participation, Management reports, Operational reports | G33: Desirable | H33: Speaker Series - EOSC: https://eosc.eu/sites/default/files/2022-05/Monitoring%20Framework.pdf, from https://eosc.eu/key-performance-indicators-KPIs-monitoring, The four pillars of governance best practice for New Zealand Directors (https://www.iod.org.nz/resources-and-insights/4-pillars-landing-page/#)
C34: Systems of accountability | E34: - | F34: e.g. Governance* holds management to account through oversight of performance and conformance matters, such as operational monitoring and evaluation | G34: Desirable | H34: The four pillars of governance best practice for New Zealand Directors (https://www.iod.org.nz/resources-and-insights/4-pillars-landing-page/#)
C35: Transparency of corporate activities | E35: - | F35: - | G35: Desirable | H35: The four pillars of governance best practice for New Zealand Directors (https://www.iod.org.nz/resources-and-insights/4-pillars-landing-page/#)
B36: Governance Structures appropriate for the specific characteristics of the commons* | E36: - | F36: e.g. steering groups or boards, including external advisors where possible e.g. board committees to target key areas of work, such as an Ethics committee - provides assurance about the commons* ethical position and monitors ethical policies and behaviours of the commons* in addition to relevant developments in the commons* community*. (e.g. staff are regularly trained in ethics, breaches of ethics are reported and investigated, liaison with stakeholders is engaged over ethical matters, ethical accountability frameworks exist and are regularly maintained) | G36: Core | H36: Phase 2 Review (Literature Analysis, November 2022 - June 2023), GORC-IG Typology, Random Encounter (SMD Data and Computing Architecture Study Workshop Series, XSEDE/ACCESS), The four pillars of governance best practice for New Zealand Directors (https://www.iod.org.nz/resources-and-insights/4-pillars-landing-page/#)
C37: Creation and maintenance of governance* structure | E37: Performed by Members* of governance* and/or supporting personnel | F37: - | G37: Core | H37: The four pillars of governance best practice for New Zealand Directors (https://www.iod.org.nz/resources-and-insights/4-pillars-landing-page/#)
D38: Characteristics of governance* structure composition, particularly on boards | E38: - | F38: e.g. balance of skills and experience, diversity, stability vs new Members*hip, size, balance between executive, non-executive, and independent directors, contributions from CEO and management, and tenure on the board including procedures for exiting the board (e.g. retirement, resignation, removal, disqualification) e.g. Community* representation in the governance* structure, such as through committees, task groups, review panels, etc. | G38: Core | H38: The four pillars of governance best practice for New Zealand Directors (https://www.iod.org.nz/resources-and-insights/4-pillars-landing-page/#) Twenty-Year Review of GBIF (https://doi.org/10.35035/ctzm-hz97)
D39: Mechanisms to maintain effective relationships between governance* elements, and management, stakeholders, and shareholders | E39: i.e. appropriate support for the board depending on scale of the commons*, such as a company secretary, corporate officer, and/or secretariat, executive committee, etc. | F39: e.g. governance* reports to funders | G39: Core | H39: The four pillars of governance best practice for New Zealand Directors (https://www.iod.org.nz/resources-and-insights/4-pillars-landing-page/#)
D40: Development and regular review of constitution(s), terms of reference, and code(s) of conduct for all governance* and management structure elements and interactions | E40: i.e. May be considered for each part or level of the governance* structure together or separately, as appropriate. Includes explicit board processes, Workload plans for the board (setting calendars and agenda items, including setting a chair and chair responsibilities) legal mandate to the governance* structure | F40: e.g. federated or multi-state commons* have the appropriate documentation for each level and component of governance* e.g. If non-profit, definition of trustees, trustee duties, and terms of trust (e.g. if reliant on volunteers, fundraising, sponsorship, grants, or member subscriptions) e.g. If state-sector, considerations for reporting to ministers and hosting departments e.g. If co-operative (stakeholders are also shareholders), compliance with local laws e.g. Code of conduct is geared for minimizing conflict and promoting debate, Board supports open debate, diversity, thoughtful challenge and constructure dissent e.g. governance* frameworks/ standards* e.g. Commitment to professional development for directors e.g. Considerations for eligibility for director appointment and their remuneration | G40: Core | H40: Phase 1 Workshop (co-located with RDA P20, 24 March 2023), The four pillars of governance best practice for New Zealand Directors (https://www.iod.org.nz/resources-and-insights/4-pillars-landing-page/#)
D41: Considerations for which committees to create on the board(s) as well as their composition, operating principles, and charter. | E41: May be permanent or temporary, created and resolved over time. e.g. audit, nomination [board succession planning], remuneration [people and human capital matters] | F41: - | G41: Desirable | H41: The four pillars of governance best practice for New Zealand Directors (https://www.iod.org.nz/resources-and-insights/4-pillars-landing-page/#)
D42: Governance* components composition and performance reviews and evaluations | E42: i.e. for board(s), committee(s), etc. | F42: e.g. Governance* accountability around policy approval and performance management | G42: Desirable | H42: The four pillars of governance best practice for New Zealand Directors (https://www.iod.org.nz/resources-and-insights/4-pillars-landing-page/#)
C43: Governance* operations and tasks regarding Management and Internal Personnel* | E43: - | F43: Human capital considerations, including workforce strategy, culture and conduct, diversity and inclusion, remuneration and performance management, succession planning, learning and development | G43: Desirable | H43: The four pillars of governance best practice for New Zealand Directors (https://www.iod.org.nz/resources-and-insights/4-pillars-landing-page/#)
B44: Management structures appropriate to the specific characteristics of the commons* | E44: - | F44: Top level management or executive level roles, such as directors, CEOs, and presidents; middle management or strategic level roles, such as senior management teach or team leads | G44: Core | H44: Task Group 1 Phase 1 Evaluation (October 2022 - April 2023), Encounter (SMD Data and Computing Architecture Study Workshop Series, XSEDE/ACCESS)
A45: Internal Commons* Policy Development, implementation, and review | E45: May be in the form of polciies, guidelines, and/or standard operating procedures (SOP) | F45: - | G45: Core | H45: Phase 1 Workshop (co-located with RDA P20, 24 March 2023)
C46: Development and regular maintenaince of policies, guidelines, and/or SOPs for resource matters | E46: - | F46: e.g. Solvency requirements (e.g. financial projections, budgets, revision of assets, value of assets, contingent liabilities) | G46: Core | H46: Task Group 1 Phase 1 Evaluation (October 2022 - April 2023)
C47: Development and regular maintenaince of policies, guidelines, and/or SOPs for commons* operations | E47: i.e. Be aware of new legislation and changes in industry practise, Assess how these changes affect the organization, Assess how the changes affect the flow of data (collection, storage, security, access), Document and communicate changes in operating procedures., Consequences for breaches, General guidelines can be in the codes of ethics, codes of conduct, codes of practise documents. | F47: e.g. global Interoperability* policy influencing standards* and protocols | G47: Core | H47: GORC-IG Typology (https://docs.google.com/document/d/19222GItDg3tcrLsDUqg9Z7GLwPELaS-XHEbN6796Tvc/edit?usp=sharing), Connolly, T., & Begg, C. (2015). Database Systems: A Practical Approach to Design, Implementation, and Management. Pearson Education Limited. ISBN: 978-1-292-06118-4
D48: Legal compliance | E48: - | F48: e.g. Legal framework, addressing compliance with applicable laws at all levels (regional, national, pan-national, etc e.g. control frameworks (COBIT, COSO), client or subject privacy, data protection, data access | G48: Desirable | H48: The four pillars of governance best practice for New Zealand Directors (https://www.iod.org.nz/resources-and-insights/4-pillars-landing-page/#), Connolly, T., & Begg, C. (2015). Database Systems: A Practical Approach to Design, Implementation, and Management. Pearson Education Limited. ISBN: 978-1-292-06118-4
D49: Commons* records and information: | E49: i.e. document management policy pertaining to commons* information and documentation (i.e. NOT ROs), | F49: e..g considerations for definition of “document”, retention period, access, User* definitions for documents, responsible individuals for documents, storage policy, storage protocols, e.g. share register e.g. Policies are versioned, indexed, and semantically annotated in a policy registry to enable broad reuse in addition to any resources mandated by policies (e.g. consent forms) e.g. implementing specific documentation framework such as https://diataxis.fr/ | G49: Core | H49: The four pillars of governance best practice for New Zealand Directors (https://www.iod.org.nz/resources-and-insights/4-pillars-landing-page/#) Turning FEAR into reality - Publications Office of the EU [2018, https://data.europa.eu/doi/10.2777/1524]
B50: Internal Code of Conduct, supplemented by ethical standards, recruitment, human resources practises, and communication of expectations | E50: A Code of Conduct, among other goals, assists in bridging the gap between legal compliance and ethics, where often legislation lags behind true ethical compliance for technology. | F50: e.g. Workplace interactions : health and safety, bullying and intimidation, employee and customer privacy, accurate reporting of information, protecting company assets, confidentiality, IP and trade secrets, computer and data security, industrial espionage, equal employment opportunities and non-discrimination, sexual harassment, conflicts of interest e.g. Financial interactions: investments, insider trading, expense account criteria and practises, gifts, entertainment, and gratuities, political contributions, compliance with local laws, global business practises e.g. Interactions with Third Parties: relationships with sellers, suppliers, contractors, joint ventures partners, etc., relationships with customers, product quality and safety, advertising and marketing practices, environmental protection, dealing with the media e.g. professional duties to the highest possible standard and carrying out duties in a legal and ethical manner are paramount.; Recognition of intellectual property rights and acknowledgement of sources; respecting privacy and confidentiality; overall concern for public health, safety, and the environment; duty to understand and comply with all relevant laws, regulations, and standards; duties to one’s superiors as well as to the public at large. | G50: Core | H50: The four pillars of governance best practice for New Zealand Directors (https://www.iod.org.nz/resources-and-insights/4-pillars-landing-page/#), Connolly, T., & Begg, C. (2015). Database Systems: A Practical Approach to Design, Implementation, and Management. Pearson Education Limited. ISBN: 978-1-292-06118-4
A51: Governance* rules, principles, and enforcement of quality for Research Objects and Services* & Tools* | E51: i.e. Research Object* ethics, including data ethics | F51: - | G51: Core
C52: Existence of a statement on the level of commitment to having Research Objects*, Services* and Tools* as open as possible and as closed as necessary, | E52: i.e. such that the commons* is demonstrating and implementing open access to the maximum extent possible while also being in compliance with all applicable laws and regulations applicable to it at all levels in addition to any frameworks and principles that are deemed required or desirable. | F52: - | G52: Core | H52: Phase 2 Evaluation (May - September 2023)
C53: Existence of a statement on the level of commitment to promoting, implementing, endorsing, and/or enforcing the FAIR principles. | E53: -Findable. Metadata* and data should be easy to find for both humans and computers. -Accessible. Once the User* finds the required data, they need to know how they can be accessed, possibly including authentication and authorisation. -Interoperable. The data usually need to be integrated with other data. In addition, the data need to interoperate with applications or workflows for analysis, storage, and processing. -Reusable. To achieve this, Metadata* and data should be well-described so that they can be replicated and/or combined in different settings. More information available at https://www.go-fair.org/fair-principles/ | F53: - | G53: Core | H53: Random Encounter (Library ethics), https://www.go-fair.org/fair-principles/
C54: Existence of a statement on the level of commitment to promoting, implementing, endorsing, and/or enforcing the CARE principles for Indigenous Data Governance*. | E54: i.e. such that the commons* considers both people and purpose in their advocacy and pursuits. Specifically, considerations for: - Collective Benefit. Data ecosystems shall be designed and function in ways that enable Indigenous Peoples to derive benefit from the data. - Authority to Control. Indigenous Peoples’ rights and interests in Indigenous data must be recognised and their authority to control such data be empowered. - Responsibility. Those working with Indigenous data have a responsibility to share how those data are used to support Indigenous Peoples’ self determination and collective benefit - Ethics. Indigenous Peoples’ rights and wellbeing should be the primary concern at all stages of the data life cycle and across the data ecosystem. More information available at https://www.gida-global.org/care. | F54: - | G54: Core | H54: Random Encounter (Library ethics), https://www.gida-global.org/care
D55: A statement on the level of commitment to equity, diversity, inclusion, and where appropriate, Indigenization (EDII*), for the commons* community | E55: - | F55: e.g. Any statement or embodiment encompassing EDII* specified in public-facing documentation, events, actions, or other programming. | G55: Desirable | H55: Random Encounter (Library ethics)
C56: For commons* with any digital Repository* aspects, existence of a statement on the level of commitment to promoting, implementing, endorsing, and/or enforcing the TRUST principles for digital Repositories*. | E56: -Transparency. To be transparent about specific Repository* Services* and data holdings that are verifiable by publicly accessible evidence. - Responsibility. To be responsible for ensuring the authenticity and integrity of data holdings and for the reliability and persistence of its Service*. - User* Focus. To ensure that the data management norms and expectations of target User* communities are met. - Sustainability*. To sustain Services* and preserve data holdings for the long-term. - Technology. To provide infrastructure and capabilities to support secure, persistent, and reliable Services*. More information available at https://www.rd-alliance.org/rda-community*-effort-trust-principles-digital-Repositories* | F56: - | G56: Core | H56: Random Encounter (Library ethics), https://doi.org/10.1038/s41597-020-0486-7
C57: Existence of a statement on the level of commitment to promoting, implementing, endorsing, and/or enforcing environmental Sustainability* in all aspects and actions of the commons*. | E57: - | F57: - | G57: Core | H57: Phase 1 Workshop (co-located with RDA P20, 24 March 2023)
C58: Where appropriate, existence of a statement on the level of commitment to upholding any other frameworks relevant to the commons*. | E58: - | F58: e.g. Paris accord e.g. considering the Sendai Framework for Disaster Risk Reduction within commons*-targeted projects and fields of research, including: Promoting the collection, analysis, management and use of relevant data (to disaster risks) and practical information and ensure its dissemination, taking into account the needs of different categories of Users*, as appropriate; Make non-sensitive hazard-exposure, vulnerability, risk, disaster and loss-disaggregated information freely available and accessible, as appropriate; Promote real time access to reliable data, make use of space and in situ information, including geographic information systems (GIS), and use information and communications technology innovations to enhance measurement Tools* and the collection, analysis and dissemination of data; To build the knowledge of government officials at all levels, civil society, communities and volunteers, as well as the private sector, through sharing experiences, lessons learned, good practices and training and education on disaster risk reduction, including the use of existing training and education mechanisms and peer learning; To promote and improve dialogue and cooperation among scientific and technological communities, other relevant stakeholders and policymakers in order to facilitate a science-policy interface for effective decision-making in disaster risk management; To ensure the use of traditional, indigenous and local knowledge and practices, as appropriate, to complement scientific knowledge in disaster risk assessment and the development and implementation of policies, strategies, plans and programmes of specific sectors, with a cross-sectoral approach, which should be tailored to localities and to the context; To strengthen technical and scientific capacity to capitalize on and consolidate existing knowledge and to develop and apply methodologies and models to assess disaster risks, vulnerabilities and exposure to all hazards; To promote investments in innovation and technology development in long-term, multi-hazard and solution-driven research in disaster risk management to address gaps, obstacles, interdependencies and social, economic, educational and environmental challenges and disaster risks; To promote the incorporation of disaster risk knowledge, including disaster prevention, mitigation, preparedness, response, recovery and rehabilitation, in formal and non-formal education, as well as in civic education at all levels, as well as in professional education and training; To promote national strategies to strengthen public education and awareness in disaster risk reduction, including disaster risk information and knowledge, through campaigns, social media and community* mobilization, taking into account specific audiences and their needs; To enhance collaboration among people at the local level to disseminate disaster risk information through the involvement of community*-based organizations and nongovernmental organizations.; To enhance the development and dissemination of science-based methodologies and Tools* to record and share disaster losses and relevant disaggregated data and statistics, as well as to strengthen disaster risk modelling, assessment, mapping, monitoring and multi-hazard early warning systems; To promote the conduct of comprehensive surveys on multi-hazard disaster risks and the development of regional disaster risk assessments and maps, including climate change scenarios; To promote and enhance, through international cooperation, including technology transfer, access to and the sharing and use of non-sensitive data and information, as appropriate, communications and geospatial and space-based technologies and related Services*; To promote common efforts in partnership with the scientific and technological community*, academia and the private sector to establish, disseminate and share good practices internationally; To support the development of local, national, regional and global User*-friendly systems and Services* for the exchange of information on good practices, cost-effective and easy-to-use disaster risk reduction technologies and lessons learned on policies, plans and measures for disaster risk reduction; To develop effective global and regional campaigns as instruments for public awareness and education, building on the existing ones; To enhance the scientific and technical work on disaster risk reduction and its mobilization through the coordination of existing networks and scientific research institutions at all levels and in all regions; To encourage the availability of copyrighted and patented materials, including through negotiated concessions, as appropriate; To enhance access to and support for innovation and technology, as well as in long-term, multi-hazard and solution-driven research and development in the field of disaster risk management e.g. https://diataxis.fr/ | G58: Desirable | H58: Sendai Framework (https://www.preventionweb.net/files/resolutions/N1516716.pdf?_gl=1*d3kn33*_ga*MjAxNDQ1NTg0MC4xNjY2NjIwOTgw*_ga_D8G5WXP6YM*MTY2NjYzMTY4My4xLjEuMTY2NjYzMTk3OS4wLjAuMA..) [2015]
C59: Ongoing review of community* rights and obligations | E59: i.e. including legal and regulatory compliance, intellectual property and copyright requirements, and data ethics | F59: - | G59: Core | H59: NIST RDaF: https://www.nist.gov/system/files/documents/2021/05/12/RDaF%20Preliminary%20Framework%20Core%2005-12-21_0.pdf, from https://www.nist.gov/programs-projects/research-data-framework-rdaf , Big Data Maturity Matrix (https://unstats.un.org/bigdata/task-teams/training/Big%20Data%20Maturity%20Matrix%20v1.0.pdf)
C60: Ongoing review of management of community* rights and obligations through accountability measures. | E60: - | F60: - | G60: Core | H60: Phase 1 Workshop (co-located with RDA P20, 24 March 2023)
C61: For Repositories* and Services* dealing with sensitive data, appropriate levels of commitment to legal and non-legal approaches that protect against sensitive information compromise | E61: - | F61: - | G61: Core | H61: Task Group 1 Phase 1 Evaluation (October 2022 - April 2023)

Sheet Rules of Participation & Access
A1: Essential Element*: Rules of Participation & Access* | C1: Items in active view: | D1: =SUBTOTAL(103, G3:G17) -> 15 | E1: - | F1: - | G1: - | H1: -
A2: Category* | B2: Subcategory* | C2: Attribute* | D2: Feature* | E2: Extended Description | F2: Examples | G2: Consideration Level* | H2: Primary Source(s)
C3: Definition of community* of Users* and Providers* | E3: i.e. any definitions or specifications on who can participate in the research commons* as a User* or Provider* with direct access and AAI rights, with reference to the audience defined in the commons* strategic plan. Depending on the policy and use, may be an operational definition. | F3: e.g. the commons* accepts Research Object* deposits from and provides Services* to anyone regardless of affiliation; the commons* accepts Research Object* deposits from and provides Services* to the hosting institution, region, country, etc. ; the commons* accepts research deposit from and provides Services* to specific entities other than the hosting entities; etc. e.g. anyone with this account type is a part of the commons by default (e.g. EGI account holders can access CSTCloud) | G3: Core | H3: Speaker Series (NII, KISTI, ARDC); re3data Data Quality Assurance Survey (Q01), Phase 2 Evaluation (May - September 2023)
A4: A set of policies defining a minimal set of rights and obligations for the commons* community | E4: May be a singular policy document with several sections addressing different aspects of rights and obligations, or several specific policies. May also be grouped with accountability in a larger rules of participation and access* document for the commons*. | F4: - | G4: Core | H4: GORC-IG Typology (https://docs.google.com/document/d/19222GItDg3tcrLsDUqg9Z7GLwPELaS-XHEbN6796Tvc/edit?usp=sharing)
B5: Access policy | E5: A legal framework for access to Research Objects*, Services* and Tools* provided by or through the commons* (i.e. computing time, digitalisation Services*, data curation etc). and sharing of Research Objects*, in addition to a Guide or policy detailing how to share Research Objects*. | F5: - | G5: Core | H5: Phase 1 Workshop (co-located with RDA P20, 24 March 2023) ; Big Data Maturity Matrix (https://unstats.un.org/bigdata/task-teams/training/Big%20Data%20Maturity%20Matrix%20v1.0.pdf)
B6: Reuse Policy | E6: A guide or policy detailing how to reuse Research Objects*, addressing intellectual property rights, data licenses, and copyright requirements. | F6: - | G6: Core | H6: Phase 2 Review (Literature Analysis, November 2022 - June 2023), https://data.research.cornell.edu/data-management/sharing/intellectual-property/
B7: Allocation of resources policy | E7: A plan for the distribution of human and technological resources in keeping with the Commons* mission or specific KPI*s | F7: - | G7: Core | H7: Phase 1 Workshop (co-located with RDA P20, 24 March 2023), Phase 2 Review (Literature Analysis, November 2022 - June 2023)
B8: Privacy policy | E8: An openly available data and Research Object* privacy policy or policies, encompassing all Research Objects* hosted by the commons* and consistent for all users*. | F8: - | G8: Core | H8: Phase 1 Workshop (co-located with RDA P20, 24 March 2023) ; GORC-WG Case Statement: https://www.rd-alliance.org/sites/default/files/GORC%20International%20Model%20WG_%20Case%20Statement%20V4%20July%202021.pdf
B9: Retention policy | E9: i.e. for Research Objects* stored or listed within the commons* | F9: Research Objects* are assessed based on their use, impact, value, uniqueness, cost, provenance*, and legal and regulatory requirements relating to preservation, considerations for technical decisions (archiving), adminitrative or policy decisions, deaccessioning and end-of-life, legal documents, Recognition of removed data (tombstone) | G9: Core | H9: Supplemental Information to the NIH Policy for Data Management and Sharing: Selecting a Repository for Data Resulting from NIH-Supported Research (https://grants.nih.gov/grants/guide/notice-files/NOT-OD-21-016.html) NIST Research Data Framework (RDaF) V1.5 (https://nvlpubs.nist.gov/nistpubs/SpecialPublications/NIST.SP.1500-18r1.pdf)
B10: Attribution policy | E10: i.e. attribution to owners and contributors on for Research Objects*, Services* and Tools* | F10: e.g. https://creativecommons.org/choose/; https://opendatacommons.org/ | G10: Core | H10: Twenty-Year Review of GBIF (https://doi.org/10.35035/ctzm-hz97)
A11: A set of policies defining minimal accountability for the commons* community | E11: May be a singular policy document with several sections addressing different aspects of accountability, or several specific policies. May also be grouped with rights and obligations in a larger rules of participation and access* document for the commons*. | F11: - | G11: Core | H11: GORC-IG Typology (https://docs.google.com/document/d/19222GItDg3tcrLsDUqg9Z7GLwPELaS-XHEbN6796Tvc/edit?usp=sharing)
B12: Acceptable Use Policy | E12: Also referred to as "terms of use", "terms of Service*", addressing Users* and Providers* of Research Objects*, Services*, and Tools* including third party Service* Providers* and the commons* on the whole. | F12: - | G12: Core | H12: Phase 1 Workshop (co-located with RDA P20, 24 March 2023)
C13: Consequences of provided Research Objects* not meeting quality expectations | E13: i.e. that supports and reflects the quality assurance process the commons* offers | F13: e.g. Metadata* is incomplete, and Providers* have some set number of days to revise and resubmit e.g. required changes for Publication* or rejection. e.g. corrupted files or format is incorrect, Providers* have some set time limit to remedy and resubmit e.g. punitive action for repeated, deliberate unqualified or inappropriate submissions or usage of Services*, such as mining bitcoin | G13: Desirable | H13: Data Quality Assurance at Research Data Repositories (re3data quality assurance survey analysis : https://datascience.codata.org/article/10.5334/dsj-2022-018/)
C14: Liability of Providers* and Users* if policies not followed | E14: i.e. For Providers* to provide Services* and Tools* and maintain appropriate behaviour in the provision of Services* and Tools*, and for Users* to use Research Objects*, Services* and Tools* appropriately for the purposes specified and within the parameters stated in the acceptable use policy. If individuals or entities in the commons community* are registered and identifiable, policies for misuse of the commons* (e.g. consequences) | F14: - | G14: Desirable | H14: Big Data Maturity Matrix (https://unstats.un.org/bigdata/task-teams/training/Big%20Data%20Maturity%20Matrix%20v1.0.pdf), Phase 2 Evaluation (May - September 2023)
D15: Consequences for breach of contract | E15: i.e. consequences for the Provider* if they breach their contract with the commons* or with individual users* | F15: - | G15: Desirable | H15: Phase 2 Evaluation (May - September 2023)
D16: Consequences for misuse of Research Objects*, Services*, Tools*, or infrastructure | E16: i.e. consequences for misuse of Services* | F16: e.g. providing HPC Services* for mining bitcoin instead of the commons* specified mandate | G16: Desirable | H16: Phase 2 Evaluation (May - September 2023)
B17: Code of Conduct | E17: Community* facing code of conduct applying to all individuals and entities in the commons* community*. Consider a people-oriented perspective for all commons* aspects and activities, such that local and global values for humans and their environment are prioritized. | F17: minimizing harm and maximizing benefit in the commons* processes from individual research objects through large-scale activities; Ethical processes address imbalances in power, resources, and how these affect the expression of human rights and any specific population rights such as Indigenous rights; The potential future use and future harm based on ethical frameworks grounded in the values and principles of the relevant community* or communities are taken into account. | G17: Core | H17: Speaker Series, found on investigation (IVOA, EOSC, ARDC, MOSP) Phase 1 Workshop (co-located with RDA P20, 24 March 2023), CARE principles

Sheet Sustainability
A1: Essential Element*: Sustainability* | C1: Items in active view: | D1: =SUBTOTAL(103, G3:G14) -> 12 | E1: - | F1: - | G1: - | H1: -
A2: Category* | B2: Subcategory* | C2: Attribute* | D2: Feature* | E2: Extended Description | F2: Examples | G2: Consideration Level* | H2: Primary Source(s)
A3: Plans, schemes, and implementations for resourcing and capacity building on the medium and long term | E3: i.e. Suitable viable plans, schemes, and implementations matching the commons* ability to execute plans, tied to the maturity and state of the commons* such that a young commons* may start at a minimal viable plan through a mature commons* focusing on scalable plans and implementations, keeping adaptability and flexibility in mind in all stages | F3: e.g. Capability mix, Financial forecast | G3: Core | H3: GORC-IG Typology (https://docs.google.com/document/d/19222GItDg3tcrLsDUqg9Z7GLwPELaS-XHEbN6796Tvc/edit?usp=sharing)
B4: Plans, schemes, and implementations for a business model sustainable on the medium and long term | E4: - | F4: a funding model with explicit stream(s) of investment and cost recovery, such as subscriptions, Service* payment models, reuse of existing components, grant applications and calls for proposals, structural funds (i.e. dedicated funding pots through hosting institution, government agency), and in-kind contributions), partnerships with industry, Mixed streams of investment and cost recovery (i.e. more than one kind of mechanism and mechanisms of different types) | G4: Core | H4: Phase 1 Workshop (co-located with RDA P20, 24 March 2023), Task Group 1 Phase 1 Evaluation (October 2022 - April 2023), GORC-IG Typology (https://docs.google.com/document/d/19222GItDg3tcrLsDUqg9Z7GLwPELaS-XHEbN6796Tvc/edit?usp=sharing), Twenty-Year Review of GBIF (https://doi.org/10.35035/ctzm-hz97)
B5: Plans, schemes, and implementations for management of human resources on the medium and long term, taking into consideration retaining accumulated knowledge | E5: i.e. business continuity practises for people, skills, expertise, documentation, etc. Relating to human capacity* and governance* | F5: strong and consistent internal documentation practises.covering team knowledge on ways of working, playbooks, practices, Tools*, documentation methods | G5: Core | H5: Phase 1 Workshop (co-located with RDA P20, 24 March 2023)
B6: Plans, schemes, and implementations for management of any other types of resources on the medium and long term. | E6: - | F6: in-kind contributions with trust consensus, structures, buildings, physical locations | G6: Optional | H6: Phase 1 Workshop (co-located with RDA P20, 24 March 2023)
A7: Plans, schemes, and implementations for medium and long term stewardship, contextualization, usability, and accessibility of Research Objects*, Services* and Tools* | E7: i.e. Suitable viable plans, schemes, and implementations addressing research object*, services*, and tools* integrity, authenticity, availability, understandability, and reusability, acknowledging potential for a wide array of systems of knowledge and communities and interests "Contextualization" here means the context of the Research Objects*, Services* and Tools*, which may be done with descriptive metadata* and documentation | F7: - | G7: Core | H7: Supplemental Information to the NIH Policy for Data Management and Sharing: Selecting a Repository for Data Resulting from NIH-Supported Research (https://grants.nih.gov/grants/guide/notice-files/NOT-OD-21-016.html) NIST Research Data Framework (RDaF) V1.5 (https://nvlpubs.nist.gov/nistpubs/SpecialPublications/NIST.SP.1500-18r1.pdf)
C8: ICT infrastructure* considerations | E8: i.e. the physical hardware and software supporting Tools* and Services* provided by or through the commons*, including relevant Standards & Conventions* and Interoperability* requirements for such changes | F8: e.g. Considerations for dealing with obsolete hardware e.g. Adaptation to emergent/disruptive technologies e.g. Maintenance/adaptation of old technologies | G8: Desirable | H8: Supplemental Information to the NIH Policy for Data Management and Sharing: Selecting a Repository for Data Resulting from NIH-Supported Research (https://grants.nih.gov/grants/guide/notice-files/NOT-OD-21-016.html) NIST Research Data Framework (RDaF) V1.5 (https://nvlpubs.nist.gov/nistpubs/SpecialPublications/NIST.SP.1500-18r1.pdf)
D9: Need to balance open data and cost recovery concerns in keeping with commons goals, needs, and resources | E9: i.e. Consideration for the balancing of openness (which the commons may need to support and develop themselves) and private support (from proprietary providers that may require restrictions on access) to match their goals, needs, and resourcing | F9: e.g. A commitment to open source infrastructure development, such as the software backend for commons* Services* and Tools* being open software such that it may be easily mapped or modified to suit Interoperability* with other Services* and Tools* | G9: Optional | H9: Phase 2 Evaluation (May - September 2023) Supplemental Information to the NIH Policy for Data Management and Sharing: Selecting a Repository for Data Resulting from NIH-Supported Research (https://grants.nih.gov/grants/guide/notice-files/NOT-OD-21-016.html) NIST Research Data Framework (RDaF) V1.5 (https://nvlpubs.nist.gov/nistpubs/SpecialPublications/NIST.SP.1500-18r1.pdf)
C10: Human resources considerations | E10: i.e. what happens to Internal Personnel* and human capacity*, governance* and management of the commons* during a scale up or scale down event(s) | F10: - | G10: Desirable | H10: Phase 2 Evaluation (May - September 2023)
C11: Commons* operations considerations | E11: i.e. what happens to commons* internal and external operations during a scale up or scale down event, relating to human capacity* and the Standards & Conventions* and Interoperability* requirements for such changes | F11: e.g. engagement* is increased or decreased in specific ways | G11: Desirable | H11: Phase 2 Evaluation (May - September 2023)
B12: Transition Plans | E12: i.e. in case the commons* ceases operations entirely, or retires a specific Service*, Tool*, or infrastructure. The goals of transition plans should be defined in strategic planning, and may be for cessation of a Service* ot Tool*, continuation by another commons* or organization, changing Services* and Tools*, and for temporary unavailability due to maintenaince or upgrades. | F12: - | G12: Desirable | H12: Supplemental Information to the NIH Policy for Data Management and Sharing: Selecting a Repository for Data Resulting from NIH-Supported Research (https://grants.nih.gov/grants/guide/notice-files/NOT-OD-21-016.html), NIST Research Data Framework (RDaF) V1.5 (https://nvlpubs.nist.gov/nistpubs/SpecialPublications/NIST.SP.1500-18r1.pdf)
B13: Scalability Plans | E13: i.e. in case of overwhelming success in funding and demand, the commons* can scale up. Conversely, a failure or slowdown in need or ability can be accomodated by a scaling down. | F13: - | G13: Desirable | H13: Phase 2 Evaluation (May - September 2023)
A14: Plans, schemes, and implementations for building community* trust and maintaining it in the long term. | E14: i.e. Suitable viable plans, schemes, and implementations with a focus on social agency to operate, relating to governance* (strategy), rules of participation and access*, and engagement*; capturing values, co-design, equity of outcomes, and the overall mindset of the commons* as well as being showcased through appropriate and accessible KPIs* and metrics*. | F14: - | G14: Core | H14: Task Group 1 Phase 1 Evaluation (October 2022 - April 2023)

Sheet Engagement
A1: Essential Element*: Engagement* | C1: Items in active view: | D1: =SUBTOTAL(103, G3:G19) -> 17 | E1: - | F1: - | G1: - | H1: -
A2: Category* | B2: Subcategory* | C2: Attribute* | D2: Feature* | E2: Extended Description | F2: Examples | G2: Consideration Level* | H2: Primary Source(s)
C3: Structured, coordinated, and implemented communication and engagement* plans and mechanisms, media, or channels | E3: - | F3: e.g. communications Tool*kit | G3: Core | H3: Phase 1 Workshop (co-located with RDA P20, 24 March 2023) ; GORC-IG Typology (https://docs.google.com/document/d/19222GItDg3tcrLsDUqg9Z7GLwPELaS-XHEbN6796Tvc/edit?usp=sharing), Task Group 2 Phase 1 Evaluation (October 2022 - April 2023) ; Big Data Maturity Matrix (https://unstats.un.org/bigdata/task-teams/training/Big%20Data%20Maturity%20Matrix%20v1.0.pdf) ; XSEDE final report (https://www.ideals.illinois.edu/items/124108) NIST Research Data Framework (RDaF) V1.5 (https://nvlpubs.nist.gov/nistpubs/SpecialPublications/NIST.SP.1500-18r1.pdf) D5.1 FAIRsFAIR Communication, Marketing and Engagement Plan [2019. FAIRsFAIR] (https://doi.org/10.5281/zenodo.6656060) D6.2 Initial Core Competence Centre Structures [2020, FAIRsFAIR] (https://doi.org/10.5281/zenodo.3732888)
D4: Intent of communications or engagement* | E4: i.e. the purpose | F4: - | G4: Core | H4: Task Group 2 Phase 2 Evaluation (May - September 2023)
D5: Content of communications or engagement* | E5: i.e. updates about the commons* structure, procedures, Services*, etc. are published and shared on a regular basis and are disseminated to Users*, or at least easily found by Users*; updates on the decision making process and what has been done with contributions, dissemination of Research Objects* hosted by the commons | F5: e.g. considerations for using appropriate and balanced diction, and in particular reducing the use of jargon. EX. Using "data description" instead of "metadata" in research-focused communication. | G5: Core | H5: Task Group 2 Phase 2 Evaluation (May - September 2023), Phase 2 Review (Literature Analysis, November 2022 - June 2023)
D6: Audience for communications or engagement* | E6: i.e. who the communications content is intended for, may influence mediums chosen for dissemination | F6: - | G6: Core | H6: Task Group 2 Phase 2 Evaluation (May - September 2023)
D7: Media and frequency for communications or engagement* | E7: i.e. how the communications material or engagement* content is shared on what platform and how often | F7: e.g. social media, blog, newsletter, journal article, supplementary material, landing pages, commons-hosted community forum, Informative events, Community* building/networking events, Strategic planning events, hackathons, etc. e.g. yearly, quarterly, monthly, daily, bi-weekly, etc. | G7: Core | H7: Task Group 2 Phase 2 Evaluation (May - September 2023)
C8: Documented and public processes of the commons maintain a high level of transparency with stakeholders and the community* | E8: Include culturally appropriate materials and translations. | F8: e.g. open of training materials and resources | G8: Desirable | H8: Phase 2 Evaluation (May - September 2023), Task Group 2 Phase 1 Evaluation (October 2022 - April 2023), Research Metadata* schemas WG, Guidelines for publishing structured Metadata on the web, Recommendation 8
A9: Community* input and feedback | E9: - | F9: e.g. community* engagement* and input as part of setting expectations for governance* decision making processes, delivery and development of Services* and Tools* | G9: Core | H9: GORC-WG Case Statement: https://www.rd-alliance.org/sites/default/files/GORC%20International%20Model%20WG_%20Case%20Statement%20V4%20July%202021.pdf
C10: Structured Feedback, to acquire input | E10: - | F10: e.g. User* feedback and community* surveys, mechanism for User* review and rating of Research Objects* (e.g. stars, text reviews, comments), Ability to report errors in the Research Object*, consultations with individuals from the research commons community* (i.e. for methodology development, benchmarking, testing), community*-driven needs assessment | G10: Core | H10: Phase 2 Evaluation (May - September 2023), Phase 1 Workshop (co-located with RDA P20, 24 March 2023), re3data Data Quality Assurance Survey, Random Encounter (Leah Wassler: https://nitter.net/LeahAWasser/status/1577730887818498049), e-infra: Resource Category, https://wiki.eoscfuture.eu/display/PUBLIC/B.+v4.00+EOSC+Resource+Profile, Data Quality Assurance at Research Data Repositories (re3data quality assurance survey analysis : https://datascience.codata.org/article/10.5334/dsj-2022-018/)
C11: Attribution and acknowledgement for contribution, once the input has been received | E11: - | F11: - | G11: Core | H11: Phase 2 Evaluation (May - September 2023), Phase 1 Workshop (co-located with RDA P20, 24 March 2023)
C12: Response to how feedback was used, once input has been actioned and feeding into creating another call for input through structured feedback | E12: - | F12: e.g. through gathering exercises, usability testing | G12: Core | H12: Phase 2 Evaluation (May - September 2023), Phase 1 Workshop (co-located with RDA P20, 24 March 2023), GORC-IG Typology (https://docs.google.com/document/d/19222GItDg3tcrLsDUqg9Z7GLwPELaS-XHEbN6796Tvc/edit?usp=sharing)
A13: Active promotion to intended audiences to participate in the commons* | E13: - | F13: e.g. Competitions and contests e.g. Facilitating community* and general population research engagement* (i.e. citizen science) e.g. Events and other outreach activities promoting standards* used and created by the commons* e.g. Encouraging data submission from recognized gaps in the commons* community, both in terms of demographic representation of Members*, Providers*, and Users* as well as topic, theme, and content-wise e.g. commons* representatives give presentations, posters, workshops, training sessions, etc. at discipline-based meetings and professional society meetings, including conference, to both promote and to empower researchers e.g. Ambassador and travelling ambassador programs, where advanced trainers “swap” (like a sabbatical) or travel to new locations to both gain experience and to introduce the commons* | G13: Core | H13: CURE-FAIR WG (https://www.rd-alliance.org/group/cure-fair-wg/outcomes/challenges-curating-reproducible-and-fair-research-output), Challenge #6 10 simple rules for improving research data discovery (https://doi.org/10.1371/journal.pcbi.1009768) Speaker Series: From KISTI, see cell GORC-IG Typology (https://docs.google.com/document/d/19222GItDg3tcrLsDUqg9Z7GLwPELaS-XHEbN6796Tvc/edit?usp=sharing) Phase 2 Evaluation (May - September 2023), Speaker Series (IVOA) Twenty-Year Review of GBIF (https://doi.org/10.35035/ctzm-hz97)
C14: Engagement with research institution librarians and information professionals | E14: - | F14: e.g. data stewards | G14: Desirable | H14: CURE-FAIR WG (https://www.rd-alliance.org/group/cure-fair-wg/outcomes/challenges-curating-reproducible-and-fair-research-output), Challenge #6
A15: Incentivisation to intended audiences to participate in or with the Commons* | E15: i.e. includes both direct incentives for participation and mitigation of disincentives for participation | F15: e.g. incentives for data publishing, deposit, research data* management e.g. remove or reduce barriers that limit data dissemination | G15: Core | H15: CURE-FAIR WG (https://www.rd-alliance.org/group/cure-fair-wg/outcomes/challenges-curating-reproducible-and-fair-research-output), Challenge #6 Phase 2 Evaluation (May - September 2023) NIST Research Data Framework (RDaF) V1.5 (https://nvlpubs.nist.gov/nistpubs/SpecialPublications/NIST.SP.1500-18r1.pdf)
B16: Consultations or events for navigating participation and access to any and all of the commons* and research domain aspects | E16: - | F16: e.g. Consultations, training, or events for navigating laws/legal structure; Training on researcher rights and responsibilities in research data* reuse and deposition into the commons* (e.g. RDM; storing, reusing, and analysing information; ethical issues about sharing data; legal and policy knowledge on open science; creating quality Metadata*) e.g. Co-creating and providing institutional processes, guidance, and incentive structures to motivate RDM best practice e.g. Encourage and enable use of commons* holdings for policy making and resource management decisions, for doing research e.g. consultations and training on meeting deposit expectations, specifically quality assurance expectations | G16: Desirable | H16: Phase 1 Workshop (co-located with RDA P20, 24 March 2023), RDA-CODATA Legal Interoperability IG Guidelines, Guideline 2D Twenty-Year Review of GBIF (https://doi.org/10.35035/ctzm-hz97)
B17: Funding competitions and/or opportunities hosted or supplied by the commons* intended for researchers (individuals, groups, organizations, etc.) to enable their research. | E17: - | F17: e.g. funding opportunities to partner with the commons* to build relevant search infrastructure e.g. Scholarship programs, to financially support graduate students and postdoctoral fellows researching the areas relevant to the commons* (e.g. scholarly Publication* and research dissemination) | G17: Desirable | H17: Speaker Series (ARDC, Alliance) Erudit 2021-2022 annual report, https://apropos.erudit.org/2021-2022-annual-report/?lang=en
A18: Engagement* with other research commons*, research infrastructure hosts, research institutions, and research funders | E18: i.e. universities, medical institutions, government agencies, etc. | F18: e.g. Mentorship, Strategic alignments.partnership e.g. The commons* acts as a connector for community* individuals and organizations to help each other | G18: Desirable | H18: Big Data Maturity Matrix (https://unstats.un.org/bigdata/task-teams/training/Big%20Data%20Maturity%20Matrix%20v1.0.pdf) Twenty-Year Review of GBIF (https://doi.org/10.35035/ctzm-hz97)
B19: Partnering on active research projects, programs, and institutes | E19: i.e. the commons partners with other organizations (committing time, funds, resournes, etc.) for discipline-specific research that may not directly address ICT or data needs. | F19: e.g. space science research projects, from design, mission development, implementation, and any relevant applications | G19: Optional | H19: Speaker Series (NeIC, AOSP)

Sheet Human Capacity
A1: Essential Element*: Human Capacity* | C1: Items in active view: | D1: =SUBTOTAL(103, G3:G29) -> 27 | E1: - | F1: - | G1: - | H1: -
A2: Category* | B2: Subcategory* | C2: Attribute* | D2: Feature* | E2: Extended Description | F2: Examples | G2: Consideration Level* | H2: Primary Source(s)
A3: Internal Capacity* | E3: - | F3: e.g. staff, volunteers, 3rd party contractors, etc. | G3: Core | H3: Phase 1 Evaluation (October 2022 - April 2023)
C4: Internal appointments preferred for all available Services*, with the intention to grow expertise for intended and future Services* | E4: i.e. such that an internal or external workforce skills inventory can be created and maintained. | F4: e.g. qualitative and quantitative data science on feedback, surveys, etc e.g. internal staff conduct their own research and/or research on behalf of the commons*, such as working on ML applications for commons* data, conducting research using commons* data e.g. Internal staff are strategically proactive in working with Providers* to address gaps in commons* holdings | G4: Core | H4: Task Group 2 Phase 1 Evaluation (October 2022 - April 2023), Big Data Maturity Matrix (https://unstats.un.org/bigdata/task-teams/training/Big%20Data%20Maturity%20Matrix%20v1.0.pdf) Section 6.11 Table 15 on pg 096, FAIRsharing WG: https://zenodo.org/record/4683794#.Yv5y13bMLIW and the National Data Services IG (https://docs.google.com/document/d/17iUyJ2icY0gFzMZGPWJyY5E0tUoukAtI4BFeRonefv4/edit?usp=sharing) NIST Research Data Framework (RDaF) V1.5 (https://nvlpubs.nist.gov/nistpubs/SpecialPublications/NIST.SP.1500-18r1.pdf) Twenty-Year Review of GBIF (https://doi.org/10.35035/ctzm-hz97)
D5: Capacity to manage administrative tasks | E5: i.e. all tasks and roles associated with internal administration and communication, tackling needs in governance* (especially management), rules of participation and access*, sustainability*, and engagement*. | F5: e.g. report writing, utilities, coordination, billing, order management, transportation, etc e.g. communications specialist, administrative assistants, secretariat, trainers, education officer, human resources staff, finance officer, etc. | G5: Core | H5: Phase 2 Review (Literature Analysis, November 2022 - June 2023), e-Infra: Resource Category https://wiki.eoscfuture.eu/display/PUBLIC/B.+v4.00+EOSC+Resource+Profile
D6: Capacity to manage operations and Infrastructure Management Services* | E6: i.e. all critical Services*, Tools*, and their supporting infrastructure are supported adequately by Internal Personnel* | F6: e.g. helpdesk Services*, monitoring, analysis, configuration, etc. e.g. technicians, resident researchers, developers, engineers, etc. | G6: Core | H6: e-Infra: Resource Category, https://wiki.eoscfuture.eu/display/PUBLIC/B.+v4.00+EOSC+Resource+Profile
D7: Commons* public record maintainer role | E7: i.e. contact person or organization for the record in a registry that describes the Repository* or other Services* operated by the commons*, the participation of the owner or maintainer of the repo* helps verify the information in the registry, such that there are Internal Personnel* who can represent the commons* and its subsidiaries | F7: - | G7: Desirable | H7: FAIRsharing WG: https://zenodo.org/record/4683794#.Yv5y13bMLIW , Phase 2 Evaluation (May - September 2023)
C8: Labour turnover/offboarding and succession/backfill plans in place | E8: i.e. a decision making process or plan for when staff leave their position (offboarding and succession) or when someone moves up in the organization (e.g. promoted). | F8: e.g. handover document, exit interviews | G8: Desirable | H8: Big Data Maturity Matrix (https://unstats.un.org/bigdata/task-teams/training/Big%20Data%20Maturity%20Matrix%20v1.0.pdf)
C9: Mechanisms for enactment of EDII* commitment for Internal Personnel* and the commons community* | E9: i.e. EDII* = Equity, Diversity, Inclusivity, Indigenization | F9: e.g. anti-discrimination processes in the recruitment process, such as evaluating anonymized resumes in the first stage of hiring | G9: Core | H9: Random Encounters (Library ethics)
C10: Documented and shared processes for every internal, personnel-facing process, maintaining a high level of transparency and documentation for and between Internal Personnel*. | E10: Include culturally appropriate materials and translations. | F10: e.g. detailed DMPs or roadmaps for: Administrative Data, Data Collection*, Documentation and Metadata*, Ethics and Legal Compliance, Storage and Backup, Selection and Preservation, Data Sharing, and Responsibilities and Resources e.g. linkage of DMPs to administrative records (e.g. agreements, transactions, etc.) e.g. Process flow for internal document management e.g. following https://diataxis.fr/ framework e.g. following The Turing Way (https://the-turing-way.netlify.app/index.html) | G10: Desirable | H10: Research Metadata* schemas WG, Guidelines for publishing structured Metadata on the web, Recommendation 8 NIST Research Data Framework (RDaF) V1.5 (https://nvlpubs.nist.gov/nistpubs/SpecialPublications/NIST.SP.1500-18r1.pdf) Speaker Series (IBICT)
C11: Regular review of Internal Personnel* working conditions and requirements | E11: i.e. who can work for, volunteer with, or represent the commons* and under what conditions, such as credentials, experience, location, etc. | F11: e.g. Careful considerations for internal staff to work onsite and be physically in one location or to have regional, pan-national, or global spread of staff. | G11: Core | H11: Twenty-Year Review of GBIF (https://doi.org/10.35035/ctzm-hz97)
A12: Skills for planning, managing and assessing Service* delivery | E12: - | F12: - | G12: Core | H12: Phase 2 Evaluation (May - September 2023)
C13: Development of use cases for Services* and platforms | E13: - | F13: - | G13: Core | H13: Random Encounter (SMD Data and Computing Architecture Study Workshop Series, XSEDE/ACCESS)
C14: Prioritization of identified needs and derived requirements of Users* | E14: - | F14: e.g. participation across integration, deployment, operations, researchers, Service* Providers* | G14: Core | H14: Random Encounter (SMD Data and Computing Architecture Study Workshop Series, XSEDE/ACCESS)
C15: Ongoing assessment of plans and deployments | E15: - | F15: e.g. review processes are conducted to ensure relevance to Users* and Providers* | G15: Core | H15: Random Encounter (SMD Data and Computing Architecture Study Workshop Series, XSEDE/ACCESS)
C16: Implementation of continuous improvement mechanism | E16: - | F16: - | G16: Core | H16: Phase 1 Workshop (co-located with RDA P20, 24 March 2023)
A17: Skill requirements for the commons* community* | E17: Requirement of any and all groups in the commons* community*, and specifically providers* and users*, which may be expected upon first contact with the commons* and/or developed via engagement* with the commons*. | F17: - | G17: Core | H17: GORC-IG Typology (https://docs.google.com/document/d/19222GItDg3tcrLsDUqg9Z7GLwPELaS-XHEbN6796Tvc/edit?usp=sharing)
C18: Documentation for easing skill requirement for the commons* community* and improving ease of use such that interacting with the commons* is an effective choice | E18: Include culturally appropriate materials and translations. | F18: e.g. following https://diataxis.fr/ framework | G18: Core | H18: Task Group 2 Phase 1 Evaluation (October 2022 - April 2023), GORC-IG Typology (https://docs.google.com/document/d/19222GItDg3tcrLsDUqg9Z7GLwPELaS-XHEbN6796Tvc/edit?usp=sharing) D3.1 FAIR policy landscape analysis [2019, FAIRsFAIR] (https://doi.org/10.5281/zenodo.5537032)
D19: Guides enabling understanding of the Rules of Participation & Access | E19: i.e. walkthroughs, statement of needed or expected skills, etc. for commons* community* groups, specifically users* and providers* | F19: e.g. Describe how Research Object*, Services* & Tools* Providers* choose the level of access to their Research Objects*, Services* & Tools* e.g. Easy to use ingest process with few barriers to participation (e.g. data deposit guidelines are supplied) e.g. How to create special collection* views or digital exhibitions e.g. Provide both single and batch ingest paths e.g. The commons* creates, maintains, and provides Metadata* crosswalks and vocabulary crosswalks e.g. Documentation about data quality and quality assurance measures performed by the commons* are available and transparent to Users* and stakeholders, preferably available in a machine-readable format. | G19: Core | H19: Task Group 2 Phase 1 Evaluation (October 2022 - April 2023) RPRD-IG matrix, GORC-IG Typology (https://docs.google.com/document/d/19222GItDg3tcrLsDUqg9Z7GLwPELaS-XHEbN6796Tvc/edit?usp=sharing), Phase 2 Evaluation (May - September 2023) Speaker Series: ARDC (mentioned during the GOSC DataIO WG update meeting in May 2022), EOSC (mentioned in GOSC DataIO webinar in July 2022) Data Quality Assurance at Research Data Repositories (re3data quality assurance survey analysis : https://datascience.codata.org/article/10.5334/dsj-2022-018/)
D20: Data Policy | E20: i.e. providing information about or action regarding: definition of the research data*, exceptions to policy, embargos, supplementary materials, data repos, data licensing, research/author support, data availability statements, data forms and standards*, mandatory data sharing (specific data types), mandatory data sharing (all papers), peer review of data, DMPs | F20: - | G20: Desirable | H20: D3.1 FAIR policy landscape analysis [2019, FAIRsFAIR] (https://doi.org/10.5281/zenodo.5537032)
A21: Ease of use for the commons* community | E21: Responsibility of the commons* to ensure that user interfaces and expectations are sufficiently easy to use and navigate. | F21: - | G21: Core | H21: Phase 2 Review (Literature Analysis, November 2022 - June 2023)
C22: Effective user-centred designs employed and tested to enable ease of use of the commons* | E22: i.e. UX design, usability are priorities in user-facing Services* & Tools* Note that this attribute specifies "user" as "end-user" which may encompass any and all commons* community* groups, and specifically providers* and users*. | F22: e.g. showcase Research Object*, Service* & Tool* accessibility (available for download, behind a paywall or login) e.g. Construct and publish a sitemap; split up large sitemaps into a sitemap index e.g. UAT (User acceptance testing) / application testing / end-user testing | G22: Core | H22: Phase 2 Evaluation (May - September 2023), Phase 1 Workshop (co-located with RDA P20, 24 March 2023) Data Discovery Paradigms: https://datascience.codata.org/articles/10.5334/dsj-2019-003/, Recommendation 3 Research Metadata schema WG (output 2, https://docs.google.com/document/d/1VTA-rFhSn6dceNZpp0Nq3mRRUoAjYMPaqQtEW-ls9Qs/edit)
A23: Training and education hosted, provided, and/or contributed to by the commons* for individuals and groups in the commons* community* | E23: - | F23: - | G23: Core | H23: Task Group 2 phase 2
C24: Development of training and education programs | E24: Consider open community driven approaches for the development of training resources, development of instructor capability, and the instruction and pedagogy principles, processes, and practices. | F24: - | G24: Core | H24: Task Group 2 phase 2
D25: Considerations for content | E25: i.e. What is being covered. | F25: e.g. preparedness for new and advancing technology, the adoption of open science practises, implementation of of FAIR principles, researcher rights and responsibilities (e.g. Research Object* structure) e.g. onboarding for commons* services* and tools*, platforms, mechanisms, etc. | G25: Core | H25: Task Group 2 Phase 1 Evaluation (October 2022 - April 2023), NIST RDaF: https://www.nist.gov/system/files/documents/2021/05/12/RDaF%20Preliminary%20Framework%20Core%2005-12-21_0.pdf, from https://www.nist.gov/programs-projects/research-data-framework-rdaf, GOSC (https://codata.org/initiatives/decadal-programme2/global-open-science-cloud/), RDA-CODATA Legal Interoperability IG Guidelines, Guideline 2D Twenty-Year Review of GBIF (https://doi.org/10.35035/ctzm-hz97)
D26: Considerations for audience | E26: i.e. who the training is for, who will participate in the training, how experienced they are as commons participants. | F26: e.g. Training for trainers, focusing on more advanced concepts, new methods, and training method; graduate students; data stewards, users, providers, etc. | G26: Core | H26: Task Group 2 Phase 1 Evaluation (October 2022 - April 2023), NIST RDaF: https://www.nist.gov/system/files/documents/2021/05/12/RDaF%20Preliminary%20Framework%20Core%2005-12-21_0.pdf, from https://www.nist.gov/programs-projects/research-data-framework-rdaf, GOSC (https://codata.org/initiatives/decadal-programme2/global-open-science-cloud/), RDA-CODATA Legal Interoperability IG Guidelines, Guideline 2D Twenty-Year Review of GBIF (https://doi.org/10.35035/ctzm-hz97)
C27: Delivery of training and education programs | E27: Includes format considerations | F27: e.g. Summer schools and/or winter schools, online courses, in-person courses, single day training, one-off training, open registration courses (open to public), graduate courses, graduate program e.g. summer school sample: D6.7 Report on schools run through franchising with local organisers [2022, FAIRsFAIR] (https://doi.org/10.5281/zenodo.6701167) e.g. higher education example: D7.3 FAIR Competence Framework for Higher Education (Data Stewardship Professional Competence Framework [2021, FAIRsFAIR] (https://doi.org/10.5281/zenodo.5361917) | G27: Core | H27: Task Group 2 Phase 1 Evaluation (October 2022 - April 2023), e-infra: Resource Category, https://wiki.eoscfuture.eu/display/PUBLIC/B.+v4.00+EOSC+Resource+Profile Speaker Series (IBICT)
C28: Evaluation and assessment of training and education programs | E28: More specific expertise needed than general community* feedback assessment | F28: - | G28: Desirable | H28: Phase 2 Evaluation (May - September 2023)
B29: Ongoing program for training Internal Personnel* | E29: i.e. to ensure Sustainability* and development of internal capacity*, such as keeping up to date with current technology and Tools* as well as building skills as the commons* Services* evolve, building internal human capacity with the support of institutional HR where applicable | F29: e.g. Product management practice and skills e.g. new and advanced technologies e.g. data management training | G29: Core | H29: Big Data Maturity Matrix (https://unstats.un.org/bigdata/task-teams/training/Big%20Data%20Maturity%20Matrix%20v1.0.pdf) NIST Research Data Framework (RDaF) V1.5 (https://nvlpubs.nist.gov/nistpubs/SpecialPublications/NIST.SP.1500-18r1.pdf)

Sheet Interoperability
A1: Essential Element*: Interoperability* | C1: Items in active view: | D1: =SUBTOTAL(103, G3:G23) -> 21 | E1: - | F1: - | G1: - | H1: -
A2: Category* | B2: Subcategory* | C2: Attribute* | D2: Feature* | E2: Extended Description | F2: Examples | G2: Consideration Level* | H2: Primary Source(s)
C3: Where appropriate and possible, addressing the need for multilingualism of commons* documentation, Services*, Tools*, engagement*, etc. | E3: - | F3: - | G3: Desirable | H3: D2.1 Report on fair requirements for persistence and Interoperability [2019, FAIRsFAIR] (https://doi.org/10.5281/zenodo.5535719)
A4: Technical Interoperability* | E4: i.e. Plans, infrastructure, and mechanisms for technical Interoperability* | F4: e.g. artifact exchange, including semantic and syntactic Interoperability* considerations, Definition: Creation and maintenance of mechanisms and plans the ability of different information technology systems and software applications to communicate and exchange Research Objects*, and specifically to accept Research Objects* from each other and perform a given task in an appropriate and satisfactory manner without the need for extra operator intervention. (https://data.europa.eu/doi/10.2777/620649) | G4: Core | H4: GORC-IG Typology (https://docs.google.com/document/d/19222GItDg3tcrLsDUqg9Z7GLwPELaS-XHEbN6796Tvc/edit?usp=sharing)
B5: Syntactic Interoperability* | E5: Plans, infrastructure, and mechanisms for syntactic Interoperability* | F5: - | G5: Core | H5: Speaker Series, originally from IVOA docs (https://www.ivoa.net/documents/index.html), Task Group 4 Phase 1 Evaluation (October 2022 - April 2023)
C6: Existence of plans and mechanisms to create and maintain Interoperability* and compatibility at the syntactic level over time | E6: - | F6: e.g. updating APIs as file formats change and evolve | G6: Core | H6: Speaker Series, originally from IVOA docs (https://www.ivoa.net/documents/index.html), Task Group 4 Phase 1 Evaluation (October 2022 - April 2023)
C7: File/data formats that support Syntactic Interoperability* | E7: - | F7: e.g. interoperable Research Object* formats E.g. enumeration of file/data formats used to encode the information represented by the digital objects* E.g. specifications on how to encode and decode the information | G7: Desirable | H7: GORC-IG Typology (https://docs.google.com/document/d/19222GItDg3tcrLsDUqg9Z7GLwPELaS-XHEbN6796Tvc/edit?usp=sharing)
C8: APIs that support Syntactic Interoperability* | E8: APIs and File/data formats are both necessary for syntactic Interoperability*, and are in a M:N relationship. One API might work with multiple file formats and one file format might be capable of processing using multiple APIs. This is why we have split them | F8: - | G8: Desirable | H8: GORC-IG Typology (https://docs.google.com/document/d/19222GItDg3tcrLsDUqg9Z7GLwPELaS-XHEbN6796Tvc/edit?usp=sharing)
B9: Semantic Interoperability* | E9: Plans, infrastructure, and mechanisms for semantic Interoperability* | F9: - | G9: Core | H9: Phase 2 Evaluation (May - September 2023), Research Metadata schema WG - Guidelines for publishing structured Metadata on the web (Rec 3), FAIR digital object Fabric IG: https://www.rd-alliance.org/sites/default/files/recommendation-jan-2017-v8_0.pdf, Component 5
C10: Existence of plans and mechanisms to create and maintain Interoperability* and compatibility at the semantic level over time | E10: - | F10: Includes creation of Semantic Objects* if necessary. e.g. The commons* develops, provides, and iteratively revises crosswalks that map the schemas that describe Research Objects* to standard markup vocabularies e.g. The commons provides definitions of a set of core types of Research Objects* and Services* provided by the commons*. E.g. Creating Semantic Artefact* that can be used to infer and map relationships between concepts and the related terms within and across vocabularies used to when encoding research information as digital objects*. | G10: Core | H10: Phase 2 Evaluation (May - September 2023) Research Metadata schema WG - Guidelines for publishing structured Metadata on the web (Rec 3) FAIR digital object Fabric IG: https://www.rd-alliance.org/sites/default/files/recommendation-jan-2017-v8_0.pdf, Component 5
C11: Metadata*, data, and other Research Objects* use standardized community*-endorsed vocabularies, and FAIR-compliant community*-endorsed vocabularies where possible. | E11: "FAIR-compliant" here means standardized with easily findable documentation. e.g. COAR vocabularies. "Community*" here encompasses research discipline and geographic location. | F11: - | G11: Desirable | H11: FAIR Data Maturity Model: https://www.rd-alliance.org/system/files/FAIR%20Data%20Maturity%20Model_%20specification%20and%20guidelines_v1.00.pdf, RDA-I2-01M and 01D
B12: Other Technical Interoperability* plans, infrastructure, and mechanisms | E12: - | F12: - | G12: Desirable | H12: Phase 2 Evaluation (May - September 2023)
C13: API s follow search standards* | E13: i.e. ROs and other commons* assets need to be findable by data Repository* and other relevant aggregators and applications. | F13: e.g. using community* adopted vocabularies for Interoperability* | G13: Desirable | H13: Data discovery paradigms (Rec 10), FAIR4RS (I1)
C14: A security framework is shared between Services* and Tools*, from backend to frontend. | E14: - | F14: Includes common encryption standards*, data exchange protocols, through User*-facing AAI interfaces such a common SSO | G14: Desirable | H14: Speaker Series, from the single-sign on for NII Services*.
A15: Organizational Interoperability* | E15: i.e. Mechanisms, infrastructure, and plans in place for organizational interoperability. Agreements between organizations, also called "pragmatic Interoperability*, how organizations align their business processes, responsibilities and expectations to achieve commonly agreed and mutually beneficial goals; meeting the requirements of the shared commons* community* by making Services* available, easily identifiable, accessible, and community* member-focused (https://data.europa.eu/doi/10.2777/620649), Considerations for Interoperability* with other commons**, repos, public research institutions, private research institutions, and commercial entities, among other entities in the community*, are included. | F15: e.g. ARDC MOU with KISTI, KISTI agreements with OpenAire and ARDC. NII has tied collaboration with CERN, MERAL, KISTI, Wacren and OpenAIRE for Interoperability*." | G15: Core | H15: GORC-IG Typology (https://docs.google.com/document/d/19222GItDg3tcrLsDUqg9Z7GLwPELaS-XHEbN6796Tvc/edit?usp=sharing)
C16: Plans and mechanisms exist to create and maintain organizational Interoperability* and compatibility over time | E16: - | F16: - | G16: Core | H16: Phase 2 Evaluation (May - September 2023)
C17: For non-domain specific commons*, domain-specific needs are addressed and considered so that the commons* is interoperable with other domain-specific commons* and Services* | E17: i.e. including both provision of specific Services* and Tools* as well as a mechanism to allow for User* or Provider*-given domain-specific extensions | F17: e.g. domain specific standards* informed by community*, domain specific Services* and Tools*, offer mappings to cross-domain vocabularies and exchange formats | G17: Desirable | H17: CURE-FAIR WG (https://www.rd-alliance.org/group/cure-fair-wg/outcomes/challenges-curating-reproducible-and-fair-research-output), Challenge #6, Task Group 4 Phase 1 Evaluation (October 2022 - April 2023)
A18: Legal Interoperability* | E18: i.e. Mechanisms, infrastructure, and plans in place for legal Interoperability*. Definition: ability to combine Research Objects* from multiple sources without conflicts among restrictions imposed by the license of each Research Object*; Research Objects* should be reusable. Covers the broad environment of laws, policies, procedures, and cooperations agreements needed to allow the seamless exchange of information and reusability of Research Objects* between difference individuals, organizations, and across jurisdictions. (https://data.europa.eu/doi/10.2777/620649) | F18: - | G18: Core | H18: RDA-CODATA Legal Interoperability IG Guidelines
C19: Access to and reuse of Research Objects* is open and unrestricted as a default rule, or otherwise granted with the fewest limitations possible | E19: i.e. such that by default, intellectual property rights are waived as far as possible and the objects distributed/made accessible in the least restrictive manner | F19: - | G19: Core | H19: RDA-CODATA Legal Interoperability IG Guidelines, Task Group 4 Phase 1 Evaluation (October 2022 - April 2023), Phase 2 Evaluation (May - September 2023)
C20: A licence for reuse is required for all Research Objects* and Tools* in the commons* | E20: i.e. the commons* requires licenses to be specified for all of its holdings, likely in the Metadata* for each Research Object* at least. | F20: e.g. distributive and permissive licenses for software and software components e.g., to make terms and conditions clear for Users* distributed across legal jurisdictions | G20: Desirable | H20: RDA-CODATA Legal Interoperability IG Guidelines, Phase 2 Evaluation (May - September 2023) SMD Policy Document SPD-41 (https://science.nasa.gov/science-red/s3fs-public/atoms/files/Scientific%20Information%20policy%20SPD-41.pdf)
C21: Licenses used are enumerated and harmonised to allow seamless exchange between actors within the commons* and outside of the commons*. | E21: - | F21: - | G21: Desirable | H21: RDA-CODATA Legal Interoperability IG Guidelines, Task Group 4 Phase 1 Evaluation (October 2022 - April 2023), Phase 2 Evaluation (May - September 2023)
C22: Who or what entities with rights to Research Objects* is/are specified appropriately via licenses and Research Object* documentation and identified before dissemination. | E22: - | F22: - | G22: Optional | H22: RDA-CODATA Legal Interoperability IG Guidelines, Task Group 4 Phase 1 Evaluation (October 2022 - April 2023), Phase 2 Evaluation (May - September 2023)
C23: Legal aspects are encoded in a Machine Actionable* format that enable automated provision of Services* and data | E23: - | F23: - | G23: Desirable | H23: RDA-CODATA Legal Interoperability IG Guidelines, Task Group 4 Phase 1 Evaluation (October 2022 - April 2023), Phase 2 Evaluation (May - September 2023)

Sheet Standards & Conventions
A1: Essential Element*: Standards & Conventions* | C1: Items in active view: | D1: =SUBTOTAL(103, G3:G35) -> 33 | E1: - | F1: - | G1: - | H1: -
A2: Category* | B2: Subcategory* | C2: Attribute* | D2: Feature* | E2: Extended Description | F2: Examples | G2: Consideration Level* | H2: Primary Source(s)
C3: Sustainability* of standards*, conventions, and guidelines | E3: i.e. Maintenance of all commons* standards and conventions*, including updates and depreciation and to check obsolescence | F3: e.g. community* standards* versions are monitored and adopted upon release e.g. new standards* and conventions are chosen when the current standard or convention becomes obsolete | G3: Core | H3: FAIRsFAIR D6.5, adapted from the idea of training material sustainability to enhance reuse
A4: Community* supported Research Object* standards and conventions | E4: - | F4: - | G4: Desirable | H4: Phase 2 Evaluation (May - September 2023)
C5: Research Object* Content | E5: i.e. required information in the Research Object*. Does not specify research-related information such as data, text, images, etc. Informs research quality assessments as part of Services* and Tools* (content or formal reviews). May have different standards* & conversions for different types of staged content, such as submission states that are raw, processed, curated, and published, | F5: e.g. Research Objects* include references to other Research Objects* e.g. Collection* content considerations, such as: collections* may contain sub-collections*, but not recursively. It should be possible to restrict this rule for individual collections*; A single collection* may contain objects stored at, and sourced from, different places; If possible, record the role of an object within a specific collection*, independent from the role it has in the context of other collections*. e.g. DMPs: Contains ‘contact’ information, including at least an identifier for a contact person, an email address, and a name. ; Contains ‘dataset’ information such as dataset ID(s) such as PIDs* or URIs, if personal data is included in the dataset, if sensitive data is included in the dataset, and the title of the dataset ; Contains ‘created’ information, such as the date and time of the first version* that is not changed in subsequent versions*. ; Contains an identifier for the DMP itself. ; Contains an indicator on whether ethical issues exist related to the data in the DMP. ; Contains ‘language’ information ; Contains ‘modified’ information, indicating the DMP version* and the date and time of the modification ; Contains a title; Data summary (What is the purpose of the data collection/generation?, What is the relation to the objectives of the project?, What types and formats of data will the project generate/collect?, Will you re-use any existing data and how?, What is the origin of the data?, What is the expected size of the data?, To whom might the data be useful ('data utility')?); Considerations for making data findable (Are the data produced and/or used in the project discoverable with Metadata*? Are the data identifiable and locatable by means of a standard identification mechanism (e.g. persistent and unique identifiers such as digital object* Identifiers)? What naming conventions do you follow? Will search keywords be provided that optimize possibilities for re-use? What is the approach for clear versioning? What Metadata* will be created? In case Metadata* standards* do not exist in your discipline, please outline what type of Metadata* will be created and how.); Considerations for making data accessible (Which data produced and/or used in the project will be made openly available as the default? If certain datasets cannot be shared (or need to be shared under restrictions), explain why, clearly separating legal and contractual reasons from voluntary restrictions. If there are restrictions on use, how will access be provided? Is there a need for a data access committee? Are there well described conditions for access (i.e. a machine readable license)? How will the identity of the person accessing the data be ascertained? How will the data be made available (e.g. by deposition in a Repository*)? What methods or software Tools* are needed to access the data? Is documentation about the software needed to access the data included? Is it possible to include the relevant software (e.g. in open source code)? Where will the data and associated Metadata*, documentation and code be deposited? Have you explored appropriate arrangements with the identified Repository*?); Considerations for making data interoperable (Are the data produced in the project interoperable, that is allowing data exchange and re-use between researchers, institutions, organisations, countries, etc. (i.e. adhering to standards* for formats, as much as possible compliant with available (open) software applications, and in particular facilitating re-combinations with different datasets from different origins)? What data and Metadata* vocabularies, standards* or methodologies will you follow to make your data interoperable? Will you be using standard vocabularies for all data types present in your data set, to allow inter-disciplinary Interoperability*? If not, will you provide mappings to more commonly used ontologies?); Considerations for making data reusable (Are data quality assurance processes described? How will the data be licensed to permit the widest reuse possible? When will the data be made available for re-use? If applicable, specify why and how long a data embargo is needed. Are the data produced and/or used in the project usable by third parties, in particular after the end of the project? If the re-use of some data is restricted, explain why. How long is it intended that the data remains re-usable?); Considerations when describing the allocation of resources: (What are the costs for making data FAIR in your project? How will these be covered? Are the resources for long term preservation discussed (costs and potential value, who decides and how what data will be kept and for how long)? Who will be responsible for data management in your project?); Considerations for data security ( What provisions are in place for data security (including data recovery as well as secure storage and transfer of sensitive data)? Is the data safely stored in certified Repositories* for long term preservation and curation? Consider the security expectations near the end of the project and during the project); Considerations for ethical aspects (Are there any ethical or legal issues that can have an impact on data sharing? These can also be discussed in the context of the ethics review. If relevant, include references to ethics deliverables and ethics chapter in the Description of the Action (DoA). Is informed consent for data sharing and long term preservation included in questionnaires dealing with personal data? Consider how existing and applicable privacy policy statements and terms of use affect the data).; Any declaration of “other issues”, such as making use of other national/funder/sectorial/departmental procedures for data management.) | G5: Desirable | H5: Phase 1 Workshop (co-located with RDA P20, 24 March 2023) FAIR data maturity model (RDA-I3-01D - useful) Research Data collections WG Recommendations (rec 5, 7, 12) DMP common standard WG (DMP common standard for machine-actionable data management plans) D1.2 Data Management Plan [2022, FAIRsFAIR] (https://doi.org/10.5281/zenodo.6656144) RPRD-IG matrix
C6: Research Object* Format | E6: i.e. how the information in the Research Object* is structured and represented. Can specify requirements for specific types of Research Objects*, informing research object quality assessment in Services* and Tools* (technical reviews) | F6: e.g. Research Object* formats shall be machine-readable, such that Research Objects* are reasonably structured to allow automated processing e.g. Files need to be converted into the most accessible formats: use of proprietary and legacy types are possible, but may be reviewed on a case by case basis e.g. Research Object* format complies with a community* standard e.g. Collection* format considerations, such as: Objects may belong to more than one collection*. e.g. DMPs are represented in a machine-actionable way | G6: Desirable | H6: Phase 1 Workshop (co-located with RDA P20, 24 March 2023) SMD Policy Document SPD-41 (https://science.nasa.gov/science-red/s3fs-public/atoms/files/Scientific%20Information%20policy%20SPD-41.pdf) RPRD-IG matrix FAIR data maturity model (RDA-R1.3-01D - essential), FAIR4RS (I1, R3), NIST RDaF Research Data collections WG Recommendations (rec 6) DMP common standard WG (DMP common standard for machine-actionable data management plans)
C7: Research Object* Access Method | E7: i.e. how the Research Object* is accessed | F7: e.g. Research Objects* are accessed through standardised protocols, preferably open and free e.g. Research Objects* can be accessed manually (i.e, with human intervention) e.g. Research Objects* can be accessed automatically (i.e. by a computer program) e.g. Variables/column names/file elements are described in both human and Machine Actionable* formats e.g. Collection* access method, such as collections* must offer well-defined actions (such as create, read, update, delete) that can be executed by software agents with minimal additional context required. e.g. the DMP can be accessed by humans or machines, automatically (without human interference) and manually (with human interference) | G7: Desirable | H7: Phase 1 Workshop (co-located with RDA P20, 24 March 2023), FAIR Maturity Indicators List (https://fairdata.Services:7171/FAIR_Evaluator/metrics) / FAIR metrics (http://www.fairmetrics.org/) FAIR data maturity model (RDA-A1-02D - essential), Persistent Identifiers: Consolidated Assertions (2.4), FAIR4RS (A), IADOPT-WG (Rec 1), Data Type Registry WG (Problem addressed by the working group) FAIR data maturity model (RDA-A1-05D), Persistent Identifiers: Consolidated Assertions (2.4) IADOPT-WG Framework (Rec 1) Research Data collections WG Recommendations (rec 10)
A8: Community* supported Metadata* standards and conventions | E8: - | F8: - | G8: Core | H8: Phase 2 Evaluation (May - September 2023)
C9: Metadata* content | E9: i.e. what information is contained in the Metadata*, with the aim to make the associated digital object* discoverable, accessible and usable/interpretable. Considerations for descriptive, structural, and administrative Metadata* | F9: Metadata* content may include (dependent on discipline, aim of the commons*, etc.): e.g. Metadata* includes information about the licence under which the Research Object* can be reused, and where possible, Metadata* refers to a standard, machine-actionable reuse licence ; e.g. A Metadata* description contains the PID* of the corresponding object; e.g. Metadata* contain qualified outward references to third party resources. This might include links to associated software, Publications*, other data sets, the author's online presence, the project's online presence, etc. instead of only listing names or titles. e.g. Metadata* contain a descriptive title beyond the title of the Research Object* filename, i.e. specifying the type of Research Object*, where the data was collected, timeframe of the data, subject of the research, and approximate size of the Research Object*. e.g. Metadata* contain a list of contributors, including those involved with curation, methodology, resources, and software (if the Research Object* is data that has been simulated or processed). e.g. Metadata* contain a rich description, including the number of files, important variables, and other available documentation. e.g. Metadata* specifies the Research Object* subtype, such as Publication* -> preprint, peer reviewed, conference proceeding, etc. e.g. Metadata* contain affiliated organizations of the authors or organizations participating in the project e.g. Metadata* contain the countries of the organization or project e.g. Metadata* contain information about the funder e.g. Metadata* contain information about the context, such as the related research community*, initiative, or infrastructure e.g. Metadata* contain the Publisher* of the Research Object* e.g. Metadata* contain information about the location of this instance of the Research Object*, such as specifying the repo, OA Publisher* or journal, aggregator, entity registries, journal aggregators, Current Research information system or CRIS e.g. Metadata* contain links to related research products, such as article and dataset, dataset and software, software and article, such that the Research Object* is part of a larger research graph e.g. Metadata* contains links or provides information for dynamic linking to related research products, such as objects by the same author, in the same context or theme focus e.g. Metadata* contain method of data production e.g. Metadata* contain information to enable the User* to get access to the data e.g. Metadata* includes references to other Metadata*, preferably qualified references e.g. Related standards* and recommendations are qualified and linked in the Metadata*, relating to both the Metadata* and the related object. e.g. Collection* Metadata* considerations, such as: It is stated, in Metadata* or otherwise, whether or not member items have an implicit ordering; If ordered, it is stated, in Metadata* or otherwise, where new items are inserted in that order; It is stated, in Metadata* or otherwise, whether member items can assume specific roles with respect to the collection* (e.g. such as becoming a 'default' item); It is stated, in Metadata* or otherwise, whether collection* Members*hip is static or mutable; It is stated, in Metadata* or otherwise, whether collection* Metadata* is static or mutable; It is stated, in Metadata* or otherwise, whether member items are restricted to a specific data type; It is stated, in Metadata* or otherwise, whether a maximum number of a Members* items is imposed e.g Software and applications have Metadata* enabling reusability e.g. Metadata* fields specific to the context of the research data*, such as Generated experimental data (source of objects/subjects, characteristics of objects/subjects, conditions of research study, specifications of instruments and Tools*, parameters for instruments and Tools*, methods protocols and calibration, data/Metadata* capture methods, provenance* capture methods, reproducibility); generated computation data (input data/Metadata*, output data/metadata, hardware, parameters and conditions for computation, versioning, data/Metadata* capture methods, provenance* and capture methods, verification/validation of output data); and so on for other contexts such as qualitative data; acquired data, critically evaluated data (numerical that's undergone rigorous review), etc. e.g. Metadata* contains information on how to appropriately cite the Research Object* | G9: Core | H9: Phase 1 Workshop (co-located with RDA P20, 24 March 2023) GORC-WG Case Statement: https://www.rd-alliance.org/sites/default/files/GORC%20International%20Model%20WG_%20Case%20Statement%20V4%20July%202021.pdf ; FAIR Data Maturity Model: https://www.rd-alliance.org/system/files/FAIR%20Data%20Maturity%20Model_%20specification%20and%20guidelines_v1.00.pdf, RDA-R1.1-01M, RDA-I3-01M - important, RDA-A1-01M FAIR digital object Fabric IG, Persistent Identifier: Consolidated Assertions - https://www.rd-alliance.org/group/fair-digital-object-fabric-ig/outcomes/persistent-identifiers-consolidated-assertions FAIR Maturity Indicators List (https://fairdata.Services:7171/FAIR_Evaluator/metrics) / FAIR metrics (http://www.fairmetrics.org/) 10 simple rules for improving research data discovery (https://doi.org/10.1371/journal.pcbi.1009768) OpenAire Monitor Methodology (https://monitor.openaire.eu/methodology/terminology) Task Group 4 Phase 1 Evaluation (October 2022 - April 2023) OpenAire Research Graph (https://graph.openaire.eu/) Speaker Series (ARDC) Data Discovery Paradigms (Rec 3), CURE-FAIR WG 10 things for curating reproducible and FAIR research (Transparency), RDAS/TDWG Attribution Metadata working group: Final recommendations FAIR4RS (F3), FAIR4RS Adoption Support (AGU: Metadata: access conditions), RDA/WDS Data publishing workflows (Data Repository entry), The FAIRsharing registry and related services (Citable, discoverable resources) Data Type Registry WG Data Type Registry Requirements Research Data collections WG Recommendations (Collection Capability 9, 10, 11, 12, 13, 14, 15) Big Data Maturity Matrix (https://unstats.un.org/bigdata/task-teams/training/Big%20Data%20Maturity%20Matrix%20v1.0.pdf) NIST Research Data Framework (RDaF) V1.5 (https://nvlpubs.nist.gov/nistpubs/SpecialPublications/NIST.SP.1500-18r1.pdf)
C10: Metadata* format | E10: i.e. how information is contained and represented in the Metadata* | F10: e.g. Metadata* terms are in a resolvable namespace (so-called Grounded Metadata*), where resolution leads to a definition of the meaning of the term such as JSON-LD, embedded schema, or any form of RDF. e.g. Metadata* uses machine-understandable community* knowledge representations and standards* e.g. Metadata* uses controlled vocabularies | G10: Core | H10: Phase 1 Workshop (co-located with RDA P20, 24 March 2023) FAIR Maturity Indicators List (https://fairdata.Services:7171/FAIR_Evaluator/metrics) / FAIR metrics (http://www.fairmetrics.org/) FAIR Data maturity model (RDA-I1-02M - important), CURE-FAIR WG 10 things for curating reproducible and FAIR research (Metadata*), FAIR4RS (F), IADOPT-WG (Rec 1) FAIR4RS (F2), 10 simple rules for improving research data discovery
C11: Metadata* access method | E11: i.e. how the Metadata* is accessed | F11: e.g. Metadata* may be retrieved by an open and free protocol. e.g. Metadata* is offered in such a way that it can be harvested and indexed e.g. Metadata* can be accessed both by humans and by machines e.g. Metadata* is accessed through standardized protocol | G11: Core | H11: Phase 1 Workshop (co-located with RDA P20, 24 March 2023) FAIR Data Maturity Model: https://www.rd-alliance.org/system/files/FAIR%20Data%20Maturity%20Model_%20specification%20and%20guidelines_v1.00.pdf, RDA-F4-01M, RDA-A1-04M - essential Task Group 4 Phase 1 Evaluation (October 2022 - April 2023), FAIR Data Maturity Model: https://www.rd-alliance.org/system/files/FAIR%20Data%20Maturity%20Model_%20specification%20and%20guidelines_v1.00.pdf, RDA-A1-02M FAIR Maturity Indicators List (https://fairdata.Services:7171/FAIR_Evaluator/metrics) / FAIR metrics (http://www.fairmetrics.org/) FAIR4RS Principles (A)
A12: Community supported Semantic Object* standards and conventions, in addition to applicable Research Object* and Metadata* standards | E12: i.e. standards and conventions* for Semantic Objects* used by the commons* as well as those hosted through the commons* as Research Objects* | F12: e.g. vocabulary and ontology standards* E.g., establishing a consensus on what information must be explicitly represented in the digital objects* themselves and to what extent the implicitly understood information should be represented elsewhere E.g., establishing a collection* of Semantic Objects* that must be referenced when representing research information as new digital objects E.g., each value and structural element used to represent a digital object* is mapped to a corresponding Semantic Object* that makes its meaning explicit and unambiguous (definitions of algorithms, procedures, scales/quantities, etc.) E.g., creating a semantic model of the commons* and its Services*, defining relationships between Services*, Semantic Objects*, Research Objects* and how they map to top-level concepts that should be understood by all participants in the commons* E.g., creating top-level Semantic Objects* that map commons* specific concepts to ubiquitous standards* and conventions beyond the commons* | G12: Desirable | H12: Phase 2 Evaluation (May - September 2023), CODATA GOSC (DataIO webinar in Nov 2022, Australia), GORC-IG Typology (https://docs.google.com/document/d/19222GItDg3tcrLsDUqg9Z7GLwPELaS-XHEbN6796Tvc/edit?usp=sharing)
C13: Semantic Object* Content | E13: i.e. what information is contained in the Semantic Object* | F13: e.g. The variables description should enable data reuse with minimum reliance on externally held free-text documentation | G13: Desirable | H13: Phase 2 Evaluation (May - September 2023) IADOPT-WG framework (Rec 2)
C14: Semantic Object* Format | E14: i.e. the container for the Semantic Object*, how the content is represented | G14: Desirable | H14: Phase 2 Evaluation (May - September 2023)
C15: Semantic Object* Access Method | E15: i.e. how the Semantic Object* is accessed | F15: e.g. machine-readable | G15: Desirable | H15: Phase 2 Evaluation (May - September 2023)
C16: The Semantic Objects* are mapped to foundational ontologies. | E16: - | F16: - | G16: Desirable | H16: D2.8 FAIR Semantics Recommendations Third Iteration [2022, FAIRsFAIR] (https://zenodo.org/record/6675295#.ZEGtUHbMLIU), P-Rec. 10
A17: Applications, Software, Services* & Tools* standards and conventions, in addition to applicable Research Object* and Metadata* standards | E17: i.e. standards and conventions* for applications and software that are both Research Objects* held by the commons* as well as those that are implemented as Services* and Tools* by the commons* | F17: - | G17: Core | H17: Phase 2 Evaluation (May - September 2023)
C18: Applications and software have demonstrated, reproducible build and distributed procedures | E18: - | F18: e.g. Test suites are included for each application and software package, i.e. the presence and quality of automated tests and the versions* of coding languages those tests are run against | G18: Desirable | H18: Random Encounter (Leah Wassler https://nitter.net/LeahAWasser/status/1577730887818498049)
C19: Relevant conventions for computational workflows | E19: - | F19: e.g. Where computational workflows are used or referenced in Provenance* information, these should be captured in a standards*-based way (i.e. is script or work-flow based so that the workflow can be re-executed using minimal actions) | G19: Desirable | H19: Task Group 4 Phase 1 Evaluation (October 2022 - April 2023), CURE-FAIR WG, 10 things for curating reproducible and FAIR research
A20: Quality standards*, conventions, and/or guidelines | E20: i.e. Guidelines that provide sufficient information to allow all Users* to readily evaluate the degree of “fitness for purpose” of their Research Objects*, Services* and Tools* before and during deposit/integration, as well as to guide internal personal on conducting quality assurance reviews of all commons* holdings as well as Services* and Tools*.These should cover all quality control and assurance criteria enacted in quality control and assurance Services* provided by and through the commons*, such as completeness, accuracy, integrity, consistency, and timeliness | F20: e.g. Repositories* have a successfully undergone a community*-endorsed certification process (such as CoreTrustSeal) | G20: Desirable | H20: NIST Research Data Framework (RDaF) V1.5 (https://nvlpubs.nist.gov/nistpubs/SpecialPublications/NIST.SP.1500-18r1.pdf) Turning FAIR into reality - Publications Office of the EU [2018, https://data.europa.eu/doi/10.2777/1524]
C21: Well-defined triggers for appraisal decisions | E21: - | F21: - | G21: Desirable | H21: NIST Research Data Framework (RDaF) V1.5 (https://nvlpubs.nist.gov/nistpubs/SpecialPublications/NIST.SP.1500-18r1.pdf)
C22: Clarity on who has the responsibility to appraise the Research Object*(s) | E22: - | F22: - | G22: Desirable | H22: NIST Research Data Framework (RDaF) V1.5 (https://nvlpubs.nist.gov/nistpubs/SpecialPublications/NIST.SP.1500-18r1.pdf)
C23: Standards and conventions* on how validation and certification of compliance towards all the other standards is done | E23: - | F23: - | G23: Desirable | H23: Turning FAIR into reality - Publications Office of the EU [2018, https://data.europa.eu/doi/10.2777/1524]
A24: Standards and conventions* for adding and maintaining PIDs* for managed assets | E24: - | F24: - | G24: Core | H24: Phase 2 Evaluation (May - September 2023)
C25: PIDs* are associated with all Research Objects*, and where available, other objects or aspects associated with the research project | E25: i.e. Some identifiable objects may not be ROs, such as digital twins of physical instruments that were not created by or for the specific research project but were used in the research project (e.g. electron microscope, spectrometer) | F25: e.g. identity management (for people), as well as for organizations, projects, funders, etc. e.g. for workflows, such as the Research Object* crate and Research Activity Identifier (RAiD) | G25: Desirable | H25: Phase 2 Evaluation (May - September 2023), Persistent Identifiers: Consolidated Assertions (PID-26, PID-30), Research Data collections WG Recommendations (Rec 1), RDA/WDS Data publishing workflows WG recommendations (research data publishing definition) NIST Research Data Framework (RDaF) V1.5 (https://nvlpubs.nist.gov/nistpubs/SpecialPublications/NIST.SP.1500-18r1.pdf) D2.1 Report on fair requirements for persistence and Interoperability [2019, FAIRsFAIR] (https://doi.org/10.5281/zenodo.5535719)
C26: Widely used and documented PID* standards* / Services* are used for assigning PID*s and for managing complex life cycles of Research Objects*. | E26: i.e. such that standard expected functions are available, even for dynamic ROs* where the information content represented in the RO* is changing for some period of time or even for an indefinite duration. | F26: e.g. The PID* records contains the Metadata* PID*, The PID* records contains the Metadata* PID*, Research Objects* are identified by a globally unique identifier, Metadata* identifier resolves to a Metadata* record, Research identifier resolves to a DO*, etc. e.g. When two or more DOs* are merged, the resulting new DO* should have a new identifier and information about the merging action should be provided in the Metadata* as provenance* Metadata* e.g. When a DO* is being split into two or more units, new identifiers should be assigned to the new entries, and some history information is made. e.g. If a DO* has been removed or deprecated, the original PID* must still be resolvable and point to tombstone information including basic Metadata*, reasons for deletion, and if available, any succeeding versions. e.g. Different versions* of Research Objects* are assigned distinct identifiers e.g. Manage replicas of Research Objects* and Research Objects* merged, split, replicated or derived from other research ("master") objects e.g. PIDs* should be human and Machine Actionable* e.g. Multiple PIDs* can point to the same Research Objects*, but not vice versa e.g. PIDs* are technology independent e.g. PID* Services* interoperate with each other e.g. PID* policy accommodates mature and established PID* practise, schemes, technologies, and Providers* e.g. Long term maintenance and Sustainability* of PID* infrastructure e.g. PIDs* used controlled syntax e.g. For sensitive data, ability to set access control and/or encryption on the kernel information e.g. Options for Providers* to have shallow FAIR (PIDs* assigned at the dataset or database level) through deep FAIR (PIDs* assigned to individual elements e.g. data points, lines) options e.g. Extrinsic identifiers for the Metadata* and intrinsic identifiers for the artifact are included for software to assist with different layers of granularity (e.g. software granularity: project, project version, modules, sub modules, snapshots, releases, commits, directories, files, fragments) | G26: Core | H26: Persistent Identifiers: Consolidated Assertions (PID-9, PID-10, PID-31, PID-32, PID-33, PID-35 through PID-43, 2.4, PID-24)) FAIR digital object Fabric IG FAIR Data maturity model (RDA-F1-02D), FAIR4RS Principles (F1), FAIR4RS Adoption support (ESMAValTool), RDA/TDWG Attribution Metadata working group: Final recommendations, Research data collections WG recommendations (Rec 2), RDA/WDS Data publishing workflows WG recommendations (research data publishing definition) FAIR4RS Principles (F1.2), FAIR4RS Adoption support (ESMAValTool*), PID information types WG (Provenance tracing: Versioning: modifying Metadata) PID information types WG (Data replication) D2.4 2nd report on FAIR requirements for persistence and Interoperability [2020, FAIRsFAIR] (https://doi.org/10.5281/zenodo.5356517) M2.15 Assessment report on 'FAIRness of software' [2020, FAIRsFAIR] (https://doi.org/10.5281/zenodo.5472911)
C27: Documented approaches are used for PID* resolution | E27: i.e. enabling PID* resolvers to be used | F27: e.g. PIDs* are assigned to data types, resolving to human and machine accessible internal or external data type standards*. If internal, data types follow the Metadata* and data format requirements applied to Research Objects* e.g. Close to 24/7 availability of all PID* Services* | G27: Core | H27: Phase 2 Evaluation (May - September 2023), Data type registry WG (problem addressed by the working group)
A28: Authentication and Authorization protocols | E28: - | F28: - | G28: Core | H28: Phase 1 Evaluation (October 2022 - April 2023), FAIR Maturity Indicators List (https://fairdata.Services:7171/FAIR_Evaluator/metrics) / FAIR metrics (http://www.fairmetrics.org/)
C29: Research Object* Authorization and Authentication, ability to implement authentication and authorization in its resolution protocol as part of the access process | E29: i.e. different access levels implemented, if applicable | F29: e.g., acceptable forms of identification e.g., specifications for Tools* and Services* to issue, validate and revoke permissions | G29: Desirable | H29: FAIR Maturity Indicators List (https://fairdata.Services:7171/FAIR_Evaluator/metrics) / FAIR metrics (http://www.fairmetrics.org/)
C30: Metadata* Authorization and Authentication, ability to implement authentication and authorization in its resolution protocol | E30: i.e. if applicable | F30: e.g., exchange format to encode information about what roles and permissions have been granted to a User* for a specific catalogue, Service* or Research Object* | G30: Desirable | H30: FAIR Maturity Indicators List (https://fairdata.Services:7171/FAIR_Evaluator/metrics) / FAIR metrics (http://www.fairmetrics.org/)
A31: Standards and conventions* for the commons* catalogues of digital objects*, including Research Objects*, Services*, and Tools* | E31: - | F31: e.g. standards* for access to information, resources, Services*, and Tools* through the commons* catalogue, such as defined Service* endpoints between any combination of humans and machines | G31: Desirable | H31: Phase 2 Evaluation (May - September 2023) Task Group 4 Phase 1 Evaluation (October 2022 - April 2023), GORC-IG Typology (https://docs.google.com/document/d/19222GItDg3tcrLsDUqg9Z7GLwPELaS-XHEbN6796Tvc/edit?usp=sharing)
A32: Standards and conventions* for regulatory and ethical compliance | E32: - | F32: - | G32: Desirable | H32: Phase 2 Evaluation (May - September 2023)
B33: Standards and conventions* for equitable access to information, resources, Services*, and Tools* | E33: In terms of equitable accessibility for individuals and groups, relating to the inclusivity of the commons* | F33: Commons* Repositories*, platforms*, Services*, and Tools* shall comply with local and international standards* for accessibility for all electronic and information technology to people with disabilities.; Commons* Repositories*, platforms*, Services*, and Tools* shall comply with a principle of non-discriminatory access so that all Users*, Providers*, staff, and other stakeholders* are treated equally. Any variation in accessibility will result solely from the capability, equipment, and connectivity of the individual." | G33: Desirable | H33: Phase 2 Evaluation (May - September 2023), SMD Policy Document SPD-41 (https://science.nasa.gov/science-red/s3fs-public/atoms/files/Scientific%20Information%20policy%20SPD-41.pdf)
B34: A response convention for detected data breaches. | E34: if needed by the commons* or required by local legislation (for instance, GDPR in Europe). May be more than one convention, as appropriate. | F34: - | G34: Optional | H34: Supplemental Information to the NIH Policy for Data Management and Sharing: Selecting a Repository for Data Resulting from NIH-Supported Research (https://grants.nih.gov/grants/guide/notice-files/NOT-OD-21-016.html)
A35: Standards and conventions* supporting and describing mechanisms, infrastructure and plans for specific workflows, use cases, and types of interexchange within the commons* | E35: Standards* and conventions* relevant for the commons* that are not captured by other categories*. | F35: e.g. Conventions describing a proven workflow to connect multiple different Research Artefact* types. Such a convention may specify that this workflow is built on a Persistent Identifier* infrastructure designed for Interoperability* ("i.e. connect related Research Objects* through their PID*. This can be done through entries in the Metadata* and/or connected platforms* (e.g. KISTI connecting DataON and AcessON with links between Research Objects* that live in DataON with articles that live on AccessON) e.g. A convention describing a process for developing, updating and promoting standards* e.g. data storage procedure, such as keeping and maintaining multiple copies e.g. standards* and conventions for commons* policies (i.e. what information to include e.g. Identify what resources and Research Objects* are to be marked up with structured Metadata* | G35: Desirable | H35: Phase 2 Evaluation (May - September 2023), GORC-WG Case Statement: https://www.rd-alliance.org/sites/default/files/GORC%20International%20Model%20WG_%20Case%20Statement%20V4%20July%202021.pdf, Task Group 4 Phase 1 Evaluation (October 2022 - April 2023) Speaker Series, IVOA: https://www.ivoa.net/documents/index.html D3.1 FAIR policy landscape analysis [2019, FAIRsFAIR] (https://doi.org/10.5281/zenodo.5537032) (Research Metadata schema WG - Guidelines for publishing structured Metadata on the web (Rec 2), Metadata Principles (#2)

Sheet ICT Infrastructure
A1: Essential Element*: ICT Infrastructure* | C1: Items in active view: | D1: =SUBTOTAL(103, G3:G30) -> 28 | E1: - | F1: - | G1: - | H1: -
A2: Category* | B2: Subcategory* | C2: Attribute* | D2: Feature* | E2: Extended Description | F2: Examples | G2: Consideration Level* | H2: Primary Source(s)
C3: Web interfaces for commons* ICT infrastructure | E3: The ability to access Services*, Tools*, and Research Objects* in a secure manner. i.e. Data and vendor independent connectivity to allow freedom of choice in the selection of the DBMS now and in the future; The ability to interface to the database independent of any proprietary Web browser or Web server; A connectivity solution that takes advantage of all the features of an organization’s DBMS; An open-architecture approach to allow interoperability with a variety of systems and technologies; A cost-effective solution that allows for scalability,growth,and changes in strategic directions, and helps reduce the costs of developing and maintaining applications; Support for transactions that span multiple HTTP requests; Acceptable performance; Minimal administration overhead; A set of high-level productivity tools to allow applications to be developed, maintained, and deployed with relative ease and speed. | F3: e.g. through using appropriate APIs, scripting languages, servers, third party services, etc. | G3: Core | H3: Connolly, T., & Begg, C. (2015). Database Systems: A Practical Approach to Design, Implementation, and Management. Pearson Education Limited. ISBN: 978-1-292-06118-4
C4: Infrastructure that is designed to scale with changing volume, complexity, and velocity of projects and expectations while ensuring baseline operations and necessary redundancy | E4: - | F4: e.g. ability to add more memory, compute power, physical components, etc. e.g. with existing hardware, ability to offload certain computing tasks to specialized hardware components within the system, enabling greater performance and efficiency e.g. implementing RAID technology, i.e. Redundant array of independent Disks. Fault tolerant, meaning the system continues running if one of the hardware components fails, specifically disk drives, disk controllers, CPU, power supplies, cooling fans. RAID levels range from 0-6 | G4: Core | H4: Big Data Maturity Matrix (https://unstats.un.org/bigdata/task-teams/training/Big%20Data%20Maturity%20Matrix%20v1.0.pdf) NIST Research Data Framework (RDaF) V1.5 (https://nvlpubs.nist.gov/nistpubs/SpecialPublications/NIST.SP.1500-18r1.pdf) Connolly, T., & Begg, C. (2015). Database Systems: A Practical Approach to Design, Implementation, and Management. Pearson Education Limited. ISBN: 978-1-292-06118-4
C5: A review and update of ICT infrastructure* happens on a regular basis | E5: i.e. ICT Infrastructure* is implemented and continuously improved to ensure reception of next generation components and mechanisms as well as to meet principles identified from higher level strategies, rules, models, and guidelines implemented by the commons* | F5: e.g. energy consumption of the infrastructure is considered | G5: Core | H5: Phase 1 Workshop (co-located with RDA P20, 24 March 2023) NIST Research Data Framework (RDaF) V1.5 (https://nvlpubs.nist.gov/nistpubs/SpecialPublications/NIST.SP.1500-18r1.pdf)
D6: Considerations for Environmental Sustainability* | E6: For all ICT infrastructure* purposes, including network, compute, storage, and cybersecurity/AAI | F6: - | G6: Core | H6: Phase 2 Evaluation (May - September 2023)
D7: Considerations for hardware maintenance, upgrades, and replacement | E7: For all ICT infrastructure* purposes, including network, compute, storage, and cybersecurity/AAI | F7: - | G7: Core | H7: Phase 2 Evaluation (May - September 2023)
D8: Considerations for software maintenance, upgrades, and replacement | E8: For all ICT infrastructure* purposes, including network, compute, storage, and cybersecurity/AAI | F8: e.g. Any security issues and responses to issues are listed | G8: Core | H8: Phase 2 Evaluation (May - September 2023) Task Group 3 Phase 1 Evaluation (October 2022 - April 2023), Random Encounter (Leah Wassler https://nitter.net/LeahAWasser/status/1577730887818498049) Report on a maturity model towards FAIR data in FAIR Repositories (D4.6) [2022, FAIRsFAIR] (https://zenodo.org/record/6699520)
A9: Network Infrastructure | E9: i.e. Ultra-fast connectivity and ubiquitous access to eInfrastructures' resources and Services*; infrastructure that enables or supports a network Service* that connects resources with stakeholders* | F9: - | G9: Core | H9: e-infra: Resource Category, https://wiki.eoscfuture.eu/display/PUBLIC/B.+v4.00+EOSC+Resource+Profile
C10: Knowledge and management of Network infrastructure | E10: - | F10: e.g. Following IEEE generic standards*, interoperable protocols | G10: Core | H10: Phase 1 Workshop (co-located with RDA P20, 24 March 2023) Phase 2 Evaluation (May - September 2023)
B11: Internal network infrastructure | E11: i.e. passing messages between connected computing and storage, Interoperability* between the endpoints for commons* computing and storage | F11: Queue, load balancer | G11: Core | H11: Phase 1 Workshop (co-located with RDA P20, 24 March 2023), Phase 2 Evaluation (May - September 2023)
B12: External network infrastructure | E12: i.e. Appropriate for the context of the commons*, considering national, regional, pan-national, and discipline/domain research community* needs and incorporating interconnect and intraconnect network infrastructure. | F12: direct connection, virtual networks, exchange connectivity, content delivery network, traffic manager Services*, and DNS | G12: Desirable | H12: Phase 1 Workshop (co-located with RDA P20, 24 March 2023), GORC-IG Typology (https://docs.google.com/document/d/19222GItDg3tcrLsDUqg9Z7GLwPELaS-XHEbN6796Tvc/edit?usp=sharing), e-infra: Resource Category, https://wiki.eoscfuture.eu/display/PUBLIC/B.+v4.00+EOSC+Resource+Profile
A13: Compute Infrastructure | E13: High-performance computing resources and scalable cloud compute capacity for demanding job processes | F13: - | G13: Core | H13: e-infra: Resource Category, https://wiki.eoscfuture.eu/display/PUBLIC/B.+v4.00+EOSC+Resource+Profile
C14: Knowledge and management of Compute Infrastructure | E14: - | F14: - | G14: Core | H14: Task Group 3 Phase 1 Evaluation (October 2022 - April 2023), GORC-IG Typology (https://docs.google.com/document/d/19222GItDg3tcrLsDUqg9Z7GLwPELaS-XHEbN6796Tvc/edit?usp=sharing), e-infra: Resource Category, https://wiki.eoscfuture.eu/display/PUBLIC/B.+v4.00+EOSC+Resource+Profile
C15: Federated Computing Infrastructure | E15: i.e. distributed computing infrastructures that are interconnected and appear as one infrastructure to the user. | F15: - | G15: Optional | H15: Speaker Series (NeIC)
B16: Base Computing Infrastructure | E16: i.e. Essential components required for stable and robust minimum viable operation | F16: job execution, workload management, orchestration, etc. | G16: Core | H16: Task Group 3 Phase 1 Evaluation (October 2022 - April 2023), GORC-IG Typology (https://docs.google.com/document/d/19222GItDg3tcrLsDUqg9Z7GLwPELaS-XHEbN6796Tvc/edit?usp=sharing), e-infra: Resource Category, https://wiki.eoscfuture.eu/display/PUBLIC/B.+v4.00+EOSC+Resource+Profile
B17: Add on Computing Infrastructure | E17: i.e. Components that enable advanced or specialzed operations | F17: virtual machine management, container management, serverless applications Repository* (i.e. cloud computing), quantum computing infrastructure, edge computing, exascale computing, etc. | G17: Optional | H17: Task Group 3 Phase 1 Evaluation (October 2022 - April 2023), GORC-IG Typology (https://docs.google.com/document/d/19222GItDg3tcrLsDUqg9Z7GLwPELaS-XHEbN6796Tvc/edit?usp=sharing), e-infra: Resource Category, https://wiki.eoscfuture.eu/display/PUBLIC/B.+v4.00+EOSC+Resource+Profile
A18: Storage Infrastructure | E18: i.e. Reliable, secure and scalable storage for scientific data, apps and workloads. | F18: - | G18: Core | H18: e-infra: Resource Category, https://wiki.eoscfuture.eu/display/PUBLIC/B.+v4.00+EOSC+Resource+Profile
C19: Knowledge and management of Storage Infrastructure | E19: - | F19: - | G19: Core | H19: Task Group 3 Phase 1 Evaluation (October 2022 - April 2023), GORC-IG Typology (https://docs.google.com/document/d/19222GItDg3tcrLsDUqg9Z7GLwPELaS-XHEbN6796Tvc/edit?usp=sharing), e-infra: Resource Category, https://wiki.eoscfuture.eu/display/PUBLIC/B.+v4.00+EOSC+Resource+Profile
C20: Federated Storage Infrastructure | E20: i.e. distributed storage infrastructure that are interconnected and appear to be one storage infrastructure to the user. | F20: - | G20: Optional | H20: Speaker Series (NeIC)
B21: Direct-attached storage, maintained and provided by the commons*, that supports different information containers as appropriate. | E21: i.e. Appropriate direct-attached Storage types (e.g. disk, tape, etc.) for appropriate information containers (e.g. object*, block*, file*) | F21: - | G21: Core | H21: Task Group 3 Phase 1 Evaluation (October 2022 - April 2023), GORC-IG Typology (https://docs.google.com/document/d/19222GItDg3tcrLsDUqg9Z7GLwPELaS-XHEbN6796Tvc/edit?usp=sharing), e-infra: Resource Category, https://wiki.eoscfuture.eu/display/PUBLIC/B.+v4.00+EOSC+Resource+Profile
B22: Network-based storage, that supports different information containers as appropriate. | E22: i.e. Cloud based storage for appropriate information containers (e.g. object*, block*, file*) | F22: - | G22: Desirable | H22: Task Group 3 Phase 1 Evaluation (October 2022 - April 2023), GORC-IG Typology (https://docs.google.com/document/d/19222GItDg3tcrLsDUqg9Z7GLwPELaS-XHEbN6796Tvc/edit?usp=sharing), e-infra: Resource Category, https://wiki.eoscfuture.eu/display/PUBLIC/B.+v4.00+EOSC+Resource+Profile
A23: Foundational Operating System (OS) | E23: - | F23: - | G23: Core | H23: Task Group 3 Phase 1 Evaluation (October 2022 - April 2023), Phase 2 Review (Literature Analysis, November 2022 - June 2023)
C24: Knowledge and management of foundational operating system | E24: - | F24: - | G24: Core | H24: Phase 2 Review (Literature Analysis, November 2022 - June 2023)
D25: Infrastructure deployment and computer resource provisioning can be automated | E25: i.e. provisioning may be done manually or automated, depending on preference, need, or context | F25: - | G25: Desirable | H25: Task Group 3 Phase 1 Evaluation (October 2022 - April 2023), Big Data Maturity Matrix (https://unstats.un.org/bigdata/task-teams/training/Big%20Data%20Maturity%20Matrix%20v1.0.pdf)
D26: Infrastructure configurations are versioned controlled and are performed through code and data pipelines | E26: Parts of technical systems should be listed, issues with technical systems and responses to issues should be listed (e.g. bug fixes, change requests) | F26: - | G26: Core | H26: Task Group 3 Phase 1 Evaluation (October 2022 - April 2023), Big Data Maturity Matrix (https://unstats.un.org/bigdata/task-teams/training/Big%20Data%20Maturity%20Matrix%20v1.0.pdf) Report on a maturity model towards FAIR data in FAIR Repositories (D4.6) [2022, FAIRsFAIR] (https://zenodo.org/record/6699520)
A27: Authentication and Authorization Infrastructure (AAI) | E27: - | F27: - | G27: Core | H27: Phase 1 Evaluation (October 2022 - April 2023)
C28: Federated Authentication and Authorization infrastructure | E28: i.e. shared AAI infrastructure with partners (e.g. with universities, research institutes, etc.) | F28: - | G28: Optional | H28: GORC-WG Case Statement: https://www.rd-alliance.org/sites/default/files/GORC%20International%20Model%20WG_%20Case%20Statement%20V4%20July%202021.pdf
B29: Base AAI Infrastructure | E29: i.e. Essential components required for minimum viable operation | F29: User* login, encrypted password storage and data | G29: Core | H29: GORC-IG Typology (https://docs.google.com/document/d/19222GItDg3tcrLsDUqg9Z7GLwPELaS-XHEbN6796Tvc/edit?usp=sharing)
B30: Add on AAI infrastructure | E30: i.e. Components that enable advanced or specialzed operations | F30: : VPN Gateway (i.e. providing secure connectivity between multiple sites. Typically a physical router device, but can also be a server, firewall, or any device with internetworking and data transmission capabilities), Multi-factor authentication, Blockchain technology, etc. | G30: Desirable | H30: e-infra: Resource Category, https://wiki.eoscfuture.eu/display/PUBLIC/B.+v4.00+EOSC+Resource+Profile

Sheet Services & Tools
A1: Essential Element*: Services* & Tools* | C1: Items in active view: | D1: =SUBTOTAL(103, G3:G76) -> 74 | E1: - | F1: - | G1: - | H1: -
A2: Category* | B2: Subcategory* | C2: Attribute* | D2: Feature* | E2: Extended Description | F2: Examples | G2: Consideration Level* | H2: Primary Source(s)
C3: Service* and Tool* maintenance and Sustainability* | E3: i.e. considerations for the improvement and consistent availability of the Service* or Tool*, such that it remains meaningful and relevant for stakeholders and viable for the commons* | F3: - | G3: Core | H3: 2.7 Framework for assessing FAIR Services [2021, FAIRsFAIR] (https://zenodo.org/record/6656431#.ZEGmHnbMLIU)
D4: Services* and Tools* undergo periodic testing and maintenance | E4: Regular maintenance and testing is planned along a reasonable timeline, services* undergo periodic testing through monitoring | F4: e,g. tests including for functional-related criteria (public-endpoints, public APIs, web interface), security-related criteria (public endpoint and APIs are secured with strong ciphers for encryption), and infrastructure-related criteria. | G4: Desirable | H4: 2.7 Framework for assessing FAIR Services [2021, FAIRsFAIR] (https://zenodo.org/record/6656431#.ZEGmHnbMLIU) A Set of Common Service Quality Assurance Baseline Criteria for Research Projects (https://digital.csic.es/handle/10261/214441)
D5: FAIR assessment | E5: i.e. Perform a self-assessment on how the functions of the Service* enable, respect or reduce each of the FAIR principles for the data it operates on. Make the results of the self-assessment publicly available, together with an outlook on the desired state for the Service* (including a cost/benefit analysis). | F5: - | G5: Desirable | H5: 2.7 Framework for assessing FAIR Services [2021, FAIRsFAIR] (https://zenodo.org/record/6656431#.ZEGmHnbMLIU), (SAF-F-5)
A6: Research Object* Repositories* | E6: i.e. a Repository* for each kind of Research Object* supported by the commons*. | F6: - | G6: Core | H6: National Data Services IG: https://docs.google.com/document/d/17iUyJ2icY0gFzMZGPWJyY5E0tUoukAtI4BFeRonefv4/edit?usp=sharing, e-infra: Resource Category, https://wiki.eoscfuture.eu/display/PUBLIC/B.+v4.00+EOSC+Resource+Profile Task Group 5 Phase 1 Evaluation (October 2022 - April 2023)
C7: API exists for automated execution of standard Repository* tasks and to interoperate with external Services* and Tools* useful to the stakeholders* | E7: - | F7: e.g. to ingest data or to integrate data analysis Services* and Tools* | G7: Desirable | H7: RPRD-IG matrix
C8: Deposit Services* and Tools* | E8: - | F8: e.g. registration, Metadata* capture, assigning of PIDs*, publishing, annotation, digitization | G8: Core | H8: e-infra: Resource Category, https://wiki.eoscfuture.eu/display/PUBLIC/B.+v4.00+EOSC+Resource+Profile FAIR digital object Fabric IG, Persistent Identifier: Consolidated Assertions - https://www.rd-alliance.org/group/fair-digital-object-fabric-ig/outcomes/persistent-identifiers-consolidated-assertions
D9: A system to register types of Research Objects*, including Metadata* schemas, that may not already be present in the commons*. | E9: i.e. during deposit, if a Research Object* type or appropriate Metadata* schema is not available already for the Research Object*, the Provider* may add the Research Object* type and appropriate Metadata* schema. This new type and Metadata* schema are then available for all future deposits from all Providers*. RO types should be based on community* standards* with the following referenced by PIDs*: - how the various dimensions represented as variables in datasets of the form w1, d2, temp, etc., correspond to real world notions of weight, distance, temperature, etc. - what are the measurement units associated with each of those dimensions, e.g., Kelvin, Celsius, or Fahrenheit in the case of temperature. - how those dimensions are grouped or packed together in datasets. | F9: - | G9: Optional | H9: FAIR digital object Fabric IG: https://www.rd-alliance.org/sites/default/files/recommendation-jan-2017-v8_0.pdf, Component 4 Turning FAIR into reality - Publications Office of the EU [2018, https://data.europa.eu/doi/10.2777/1524] D2.1 Report on fair requirements for persistence and Interoperability [2019, FAIRsFAIR] (https://doi.org/10.5281/zenodo.5535719)
C10: Research Object* validation Tool* | E10: - | F10: e.g. for data, for Research Software*, etc. e.g. should allow Users* to capture and store the evaluation as provenance* data. | G10: Desirable | H10: Speaker Series (ARDC), FAIR4RS NIST Research Data Framework (RDaF) V1.5 (https://nvlpubs.nist.gov/nistpubs/SpecialPublications/NIST.SP.1500-18r1.pdf) Twenty-Year Review of GBIF (https://doi.org/10.35035/ctzm-hz97)
C11: Research Object* FAIR self-assessment Tool* | E11: - | F11: e.g. for data, for Research Software*, etc. e.g. may include a scale of FAIRness or a scale for each aspect. e.g. should allow Users* to capture and store the evaluation as provenance* data. | G11: Desirable | H11: FAIR4RS
C12: Integrity and quality control mechanisms for Metadata*, including immutability | E12: - | F12: - | G12: Desirable | H12: RDA/WDS Data publishing Workflows WG Recommendations Data Quality Assurance at Research Data Repositories (re3data quality assurance survey analysis : https://datascience.codata.org/article/10.5334/dsj-2022-018/)
D13: Technical | E13: - | F13: e.g. format and vocabulary quality and control mechanisms for Metadata*, compliant with an appropriate Metadata* schema, Metadata* application is consistent with other Metadata* records in the collection*) | G13: Desirable | H13: RDA/WDS Data publishing Workflows WG Recommendations Data Quality Assurance at Research Data Repositories (re3data quality assurance survey analysis : https://datascience.codata.org/article/10.5334/dsj-2022-018/)
D14: Completeness | E14: i.e. all necessary Metadata* fields are sufficiently filled | F14: e.g. copyrights and usage rights are clarified, information on data provenance*) | G14: Desirable | H14: RDA/WDS Data publishing Workflows WG Recommendations Data Quality Assurance at Research Data Repositories (re3data quality assurance survey analysis : https://datascience.codata.org/article/10.5334/dsj-2022-018/)
D15: Content Quality | E15: - | F15: e.g. checking function of outgoing links, appropriateness | G15: Optional | H15: RDA/WDS Data publishing Workflows WG Recommendations Data Quality Assurance at Research Data Repositories (re3data quality assurance survey analysis : https://datascience.codata.org/article/10.5334/dsj-2022-018/)
D16: FAIR compliance | E16: FAIR compliance to the maximum degree possible | F16: - | G16: Optional | H16: RDA/WDS Data publishing Workflows WG Recommendations Data Quality Assurance at Research Data Repositories (re3data quality assurance survey analysis : https://datascience.codata.org/article/10.5334/dsj-2022-018/)
C17: Integrity and quality control mechanisms for Research Objects* | E17: - | F17: - | G17: Desirable | H17: re3data Data Quality Assurance Survey
D18: QA/QC are implemented with several methods or mechanisms, including assessment of Publications*, research data*, and Research Software* | E18: - | F18: e.g. a combination of curators, peer review, User* feedback or machine, etc | G18: Desirable | H18: Research Platforms for Research Data IG: https://www.rd-alliance.org/group/repository-platforms-research-data-ig/outcomes/matrix-use-cases-and-functional-requirements, Task Group 5 Phase 1 Review (Literature Analysis, August - October 2022)
D19: Formal criteria are applied to ensure technical quality of Research Objects*, conducted internally by the commons*. | E19: Can be automatic. | F19: e.g. file format such as open data format, licence such as open data licence physical integrity, # of datasets is correct, size of datasets is >0, datasets and Metadata* are accessible, data sizes are controlled and correct, Metadata* is consistent to the data, data and descriptions are consistent), administrative (e.g. openness, described in open documentation, consent forms from study subjects are available, conflicts of interest are declared, the title, PID*, version, data producer, Publication* or update date, Publisher*, date accessed, and usage licence are included, data with commercial value have a filed patent), and access-related quality of the Research Object* (e.g. availability), testing and validation Tools* for software, including reproducibility and uncertainty quantification and system resilience and adaptability | G19: Desirable | H19: re3data Data Quality Assurance Survey (Q05), e-infra: Resource Category, https://wiki.eoscfuture.eu/display/PUBLIC/B.+v4.00+EOSC+Resource+Profile (Validation), Task Group 5 Phase 1 Review (Literature Analysis, August - October 2022) NIST Research Data Framework (RDaF) V1.5 (https://nvlpubs.nist.gov/nistpubs/SpecialPublications/NIST.SP.1500-18r1.pdf)
D20: A review is conducted to ensure content quality of the Research Object* | E20: May be conducted externally by expert reviewers | F20: e.g. data accuracy, appropriate and correct use of methods, completeness, compliance with legal and ethical norms, consistency, plausibility/correctness, novelty, reproducibility, significance, data logic and organization, suitability, temporal and spatial coverage where appropriate, reuse potential, pass statistical tests, documentation quality and appropriateness, software executability, structure, interpretability, objectivity, traceability, understandability, error documentation, precision, trustworthiness (origin, methods of collecting and processing, authenticity, acceptability, applicability, understandability, subject, discipline, reputation of creators, biases of the evaluators, Users*’ confidence, lack of deception, independent review, reuse), ease of use, e.g. for software specifically, Continuous integration and continuous delivery pipelines (CI/CD), encompassing both verification and validation processes for functional (behaviour-driven) and non-functional (usability-oriented) requirements as well as automation. | G20: Optional | H20: re3data Data Quality Assurance Survey (Q10)
D21: Relevance of the Research Object* to the commons* is determined | E21: i.e. does it follow the theme of the commons* | F21: - | G21: Desirable | H21: Task Group Phase 1 Evaluation (October 2022 - April 2023)
D22: Research Objects* are FAIR compliant to the maximum degree possible | E22: i.e. the FAIRness of the object is assessed. May be automated) (e.g. Quality control for PIDs* to check if they are at an appropriate FAIRness depth and do not duplicate existing PIDs* | F22: - | G22: Optional | H22: Data Quality Assurance at Research Data Repositories (re3data quality assurance survey analysis : https://datascience.codata.org/article/10.5334/dsj-2022-018/), D2.4 2nd report on FAIR requirements for persistence and Interoperability [2020, FAIRsFAIR] (https://doi.org/10.5281/zenodo.5356517)
C23: Storage Services* and Tools* | E23: i.e. management of storage infrastructure to meet needs of Users*, ideally with capacity for temporary, campaign/project, community*, and long-term storage, or hot, warm, and cold storage options | F23: E.G. backups, synchronization between copies, replication, recovery ability, long-term digital preservation / cold storage, archive storage e.g. Policy-based storage Services*, including access control and higher security measures where necessary e.g. Direct management and curation: Flexible methods to track usage and to specify and enforce limits (e.g. User* quotas, tree quotes, etc.); Methods to quickly walk the storage resource namespace (distribution of file or object sizes, access frequencies, etc.); Ability to manage hardware that has different characteristics (e..g bandwidth, capacity) | G23: Core | H23: Task Group 3 Phase 1 Evaluation (October 2022 - April 2023), GORC-IG Typology (https://docs.google.com/document/d/19222GItDg3tcrLsDUqg9Z7GLwPELaS-XHEbN6796Tvc/edit?usp=sharing), e-infra: Resource Category, https://wiki.eoscfuture.eu/display/PUBLIC/B.+v4.00+EOSC+Resource+Profile Storage 2020: A Vision for the Future of HPC Storage [2017] (https://escholarship.org/uc/item/744479dp)
C24: Digital badges for Research Objects*, with features for online sharing, verification, portability, and trustworthiness with associated Metadata* | E24: - | F24: e.g. expose Research Object* usage statistics so that they are publicly viewable on the Research Object* landing page, spanning access and downloads (E.G. Metadata* viewed, object viewed, object downloaded, object cited, map view of geographic distribution, cumulative views, citations, number and distribution of linked objects, etc.) e.g. Make the quality of individual datasets visible so that they are publicly viewable on the Research Object* landing page e.g. to allow filtering of raw data by quality check issue and provide statistics and metrics* on the selected records to find gross anomalies and guide selection | G24: Optional | H24: SQAaaS (https://sqaaas.eosc-synergy.eu/#/) Data Discovery Paradigms: https://datascience.codata.org/articles/10.5334/dsj-2019-003/, Recommendation 6 ; e-infra: Resource Category, https://wiki.eoscfuture.eu/display/PUBLIC/B.+v4.00+EOSC+Resource+Profile (Publication, analysis) Data Quality Assurance at Research Data Repositories (re3data quality assurance survey analysis : https://datascience.codata.org/article/10.5334/dsj-2022-018/) Twenty-Year Review of GBIF (https://doi.org/10.35035/ctzm-hz97)
B25: Research data* Repository* | E25: Vast range of datasets and other research data* objects to facilitate research and scientific activities that have been provided by the commons* community*. Different kinds of data Repositories* may need different types of management. | F25: Metadata*, government and agency data, statistical data, scientific and research data*, online Service* data, clinical trial data, epidemiological data, etc | G25: Core | H25: National Data Services IG: https://docs.google.com/document/d/17iUyJ2icY0gFzMZGPWJyY5E0tUoukAtI4BFeRonefv4/edit?usp=sharing, e-infra: Resource Category, https://wiki.eoscfuture.eu/display/PUBLIC/B.+v4.00+EOSC+Resource+Profile
B26: Publication* and research documentation Repository* | E26: i.e. Research findings available to the wider academic community* and beyond.) that have been provided by the commons* community* | F26: workflow Repository*, peer-reviewed article Repository*, reports and notes Repository* | G26: Core | H26: e-infra: Resource Category, https://wiki.eoscfuture.eu/display/PUBLIC/B.+v4.00+EOSC+Resource+Profile
B27: Research Software* Repository* | E27: i.e. Research Software* that has been provided by the commons* community* ; a catelogue of software items, including platforms*, packages, notebooks and libraries , included documentation and links for dependencies required to deploy but not all dependent libraries will be required to be part of the software Repository*. The software repo* can either have Metadata* for items held within the repo* or can point to dos in external platforms* (e.g. github)) | F27: - | G27: Core | H27: e-infra: Resource Category, https://wiki.eoscfuture.eu/display/PUBLIC/B.+v4.00+EOSC+Resource+Profile
B28: Semantic Object* Repository* | E28: i.e. catalogue of vocabulary and ontology schemas, where Users* and Providers* can search, find, and use these schemas as well as add, register, and maintain concept vocabularies not already present | F28: - | G28: Core | H28: Task Group 5 Phase 1 Evaluation (October 2022 - April 2023)
A29: Discovery Services* | E29: i.e. a platform* or portal to discover Research Objects*, passive interaction | F29: E.G. sharing and discovery Services* including enabling sharing and downloading of bibliographic references where applicable, providing a range of query interfaces and access points such as simple search box, advanced search, subject search, and faceted browser/filtering | G29: Core | H29: e-infra: Resource Category, https://wiki.eoscfuture.eu/display/PUBLIC/B.+v4.00+EOSC+Resource+Profile
C30: Harvesting, or aggregating, Metadata* from external Repositories* and commons*, including Members* and Providers* | E30: - | F30: e.g. from institutional Repositories*, from commons* with whom a MOU is shared | G30: Desirable | H30: Task Group 5 Phase 1 Evaluation (October 2022 - April 2023) e-infra: Resource Category, https://wiki.eoscfuture.eu/display/PUBLIC/B.+v4.00+EOSC+Resource+Profile
C31: Provide a harvestable Metadata* Service* so that others can harvest Metadata* hosted by the commons* that describe Research Objects*, Services*, and Tools*. | E31: - | F31: - | G31: Desirable | H31: Task Group 5 Phase 1 Evaluation (October 2022 - April 2023)
A32: Services* and Tools* for direct research tasks | E32: - | F32: e.g. Aggregation Tools*, surveying Tools*, statistical Tools*, calculation and analysis Tools*, APIs, Database management Tools*, testing and validation Tools* | G32: Core | H32: e-infra: Resource Category, https://wiki.eoscfuture.eu/display/PUBLIC/B.+v4.00+EOSC+Resource+Profile NIST Research Data Framework (RDaF) V1.5 (https://nvlpubs.nist.gov/nistpubs/SpecialPublications*/NIST.SP.1500-18r1.pdf
C33: Consultation Services* offered to the commons* community* to improve or facilitate research. | E33: i.e. May be automated, in a "ticket" or "chat" format with personnel, or through meetings with personnel. May be offered on an individual and/or group basis. | F33: e.g. Audit and Assessment, Application porting, application scaling, Application optimization, Software development, Software improvement, Modeling and simulation, Prototype development, Testing, Certification, Calibration, Benchmarking, Technology Transfer, Methodology Development e.g. The commons* works with Providers* if consistent data quality issues are found over time such that direct, individualized support for Research Object* Providers* is available | G33: Desirable | H33: e-infra: Resource Category, https://wiki.eoscfuture.eu/display/PUBLIC/B.+v4.00+EOSC+Resource+Profile Twenty-Year Review of GBIF (https://doi.org/10.35035/ctzm-hz97) Data Quality Assurance at Research Data Repositories (re3data quality assurance survey analysis : https://datascience.codata.org/article/10.5334/dsj-2022-018/)
C34: Platform* as a Service* (PaaS) | E34: i.e. space(s) to deploy, develop and use software packages and libraries, where ideally both graphical and code interfaces to platforms* are available | F34: - | G34: Desirable | H34: e-infra: Resource Category, https://wiki.eoscfuture.eu/display/PUBLIC/B.+v4.00+EOSC+Resource+Profile
D35: Developer Tools* | E35: i.e. to develop your own research Service* or Tool*, e.g. simulation Tools* | F35: - | G35: Optional | H35: e-infra: Resource Category, https://wiki.eoscfuture.eu/display/PUBLIC/B.+v4.00+EOSC+Resource+Profile
D36: Software Development Kits | E36: - | F36: - | G36: Optional | H36: e-infra: Resource Category, https://wiki.eoscfuture.eu/display/PUBLIC/B.+v4.00+EOSC+Resource+Profile
D37: Software Libraries | E37: i.e. focused on developing more complete or complex software that Services* a direct research purpose | F37: - | G37: Desirable | H37: e-infra: Resource Category, https://wiki.eoscfuture.eu/display/PUBLIC/B.+v4.00+EOSC+Resource+Profile
D38: APIs Repository*/ Gateway | E38: - | F38: - | G38: Desirable | H38: e-infra: Resource Category, https://wiki.eoscfuture.eu/display/PUBLIC/B.+v4.00+EOSC+Resource+Profile
D39: Training platform* and Tools* | E39: i.e. a portal, interface, etc. where individuals in the commons* community* can access training materials, modules, courses, etc. and complete asynchronously or synchronously | F39: - | G39: Optional | H39: e-infra: Resource Category, https://wiki.eoscfuture.eu/display/PUBLIC/B.+v4.00+EOSC+Resource+Profile
B40: Data acquisition Services* and Tools* | E40: i.e. for the collection and ingest of data | F40: - | G40: Core | H40: Phase 2 Evaluation (May - September 2023)
B41: Analysis, processing, and visualization Services* and Tools* | E41: i.e. Processes for Research Objects* with the goal of discovering useful information, informing conclusions, and supporting decision-making. | F41: artificial intelligence and machine learning Services* and Tool*ls, forecasting, visualization, data extrapolation, image analysis, iterative model fitting. data analysis (e.g. transformation, calibration, normalization, plausibility checks), data cleaning, etc., Different forms and formats of Analysis (i.e. manual, exploratory, descriptive, diagnostic, evaluative, predictive, prescriptive, correlational, statistical, automated or autonomous) e.g. workflows (i.e. Services* enabling the building and implementation of workflows), A collaborative platform* with AAI for groups") | G41: Core | H41: GORC-IG Typology (https://docs.google.com/document/d/19222GItDg3tcrLsDUqg9Z7GLwPELaS-XHEbN6796Tvc/edit?usp=sharing), NIST Research Data Framework (RDaF) V1.5 (https://nvlpubs.nist.gov/nistpubs/SpecialPublications/NIST.SP.1500-18r1.pdf), e-infra: Resource Category, https://wiki.eoscfuture.eu/display/PUBLIC/B.+v4.00+EOSC+Resource+Profile, Data Discovery Paradigms: https://datascience.codata.org/articles/10.5334/dsj-2019-003/, Recommendation 7 and FAIRsharing WG recommendation: https://zenodo.org/record/4683794#.Yv5y13bMLIW, Task Group 5 Phase 1 Evaluation (October 2022 - April 2023)
B42: Data collection and Research Object* Management Services* and Tools* | E42: i.e. active data management' Tools*, active Research Object* management Tools*, such as an RDM platform | F42: Access, transfer, interlinking, anonymisation, preservation, brokering; creation, maintenance and curation of objects and their versions, Identify and aggregate Metadata* records that describe the same Research Object*, record audit trails, transfer ownership, setting and automation of policies on Research Objects*, updates are permitted by the Provider* (e.g. software updates, automatic or asynchronous updates), collections management, automatically generated Metadata*, LIMS, ELNS, Tools* dealing with specialist types of data such as colony management systems for animal data e.g. DMP platform*, DMP Repository*, DMP development Services* and Tools*, Software Management Plan capacity such as Tool* or platform* | G42: Core | H42: GORC-IG Typology (https://docs.google.com/document/d/19222GItDg3tcrLsDUqg9Z7GLwPELaS-XHEbN6796Tvc/edit?usp=sharing), NIST Research Data Framework (RDaF) V1.5 (https://nvlpubs.nist.gov/nistpubs/SpecialPublications/NIST.SP.1500-18r1.pdf)" e-infra: Resource Category, https://wiki.eoscfuture.eu/display/PUBLIC/B.+v4.00+EOSC+Resource+Profile, Task Group 5 Phase 1 Evaluation (October 2022 - April 2023), FAIR Data Maturity Model: https://www.rd-alliance.org/system/files/FAIR%20Data%20Maturity%20Model_%20specification%20and%20guidelines_v1.00.pdf, RDA-A2-01M, Data Discovery Paradigms (Rec 8), RPRD-IG matrix, Research Data collections WG Recommendations - Service feature 3, Big Data Maturity Matrix (https://unstats.un.org/bigdata/task-teams/training/Big%20Data%20Maturity%20Matrix%20v1.0.pdf), Random Encounter (Leah Wassler https://nitter.net/LeahAWasser/status/1577730887818498049), Research Data collections WG Recommendations National Data Services IG: https://docs.google.com/document/d/17iUyJ2icY0gFzMZGPWJyY5E0tUoukAtI4BFeRonefv4/edit?usp=sharing, Speaker Series: presentations and analysis ((NII, ARDC, EOSC, KISTI, MOSP) )
A43: Services* and Tools* that enable workflows and middleware | E43: - | F43: e.g. Communication (such as a reporting Service*, to assist Users*, Providers*, and other stakeholders* in creating necessary reports that use or include the commons* (e.g. impact of commons* on dissemination of the Provider*'s data), collaboration, productivity, business, education, social/networking, utilities e.g. automated Metadata* capture, anomaly detection and correction Tools*, collaboration Tools*, process monitoring and evaluation tracking Tools*, containerization Tools*, workflow component reuse Tool*, microServices*, Tools* enabling distributed workflows, comprehensive report generation Tool* | G43: Desirable | H43: e-infra: Resource Category, https://wiki.eoscfuture.eu/display/PUBLIC/B.+v4.00+EOSC+Resource+Profile NIST Research Data Framework (RDaF) V1.5 (https://nvlpubs.nist.gov/nistpubs/SpecialPublications/NIST.SP.1500-18r1.pdf)
A44: Persistent Identifier* Services* | E44: i.e. assigning of PIDs*, mediating external PID* Services* such as DOI, ORCID, RAiD, etc. | F44: - | G44: Core | H44: e-infra: Resource Category, https://wiki.eoscfuture.eu/display/PUBLIC/B.+v4.00+EOSC+Resource+Profile FAIR digital object Fabric IG, Persistent Identifier: Consolidated Assertions - https://www.rd-alliance.org/group/fair-digital-object-fabric-ig/outcomes/persistent-identifiers-consolidated-assertions Turning FAIR into reality - Publications Office of the EU [2018, https://data.europa.eu/doi/10.2777/1524]
C45: Use of a global PID* Service* that ensures continuous resolvability of PIDs* | E45: - | F45: - | G45: Core | H45: FAIR digital object Fabric IG, Persistent Identifier: Consolidated Assertions - https://www.rd-alliance.org/group/fair-digital-object-fabric-ig/outcomes/persistent-identifiers-consolidated-assertions Turning FAIR into reality - Publications Office of the EU [2018, https://data.europa.eu/doi/10.2777/1524]
D46: Persistence of the identifier | E46: i.e. uniqueness | F46: - | G46: Core | H46: https://andrew.treloar.net/research/diagrams/five_persistences.html FAIR digital object Fabric IG, Persistent Identifier: Consolidated Assertions - https://www.rd-alliance.org/group/fair-digital-object-fabric-ig/outcomes/persistent-identifiers-consolidated-assertions Turning FAIR into reality - Publications Office of the EU [2018, https://data.europa.eu/doi/10.2777/1524]
D47: Persistence of the binding between identifier and object | E47: - | F47: - | G47: Core | H47: https://andrew.treloar.net/research/diagrams/five_persistences.html
D48: Persistence of the Services* to resolve from the identifier to the object | E48: i.e. resolvability | F48: - | G48: Core | H48: https://andrew.treloar.net/research/diagrams/five_persistences.html FAIR digital object Fabric IG, Persistent Identifier: Consolidated Assertions - https://www.rd-alliance.org/group/fair-digital-object-fabric-ig/outcomes/persistent-identifiers-consolidated-assertions Turning FAIR into reality - Publications Office of the EU [2018, https://data.europa.eu/doi/10.2777/1524]
D49: Persistence of Service* to allow for updating of the binding between identifier and object | E49: - | F49: e.g. if the object is not longer available, the binding between PID* and object can be updated so that the PID* points to tombstone information | G49: Desirable | H49: https://andrew.treloar.net/research/diagrams/five_persistences.html
C50: Capacity to discover PIDs* from Metadata* and vice versa | E50: - | F50: - | G50: Core | H50: FAIR digital object Fabric IG, Persistent Identifier: Consolidated Assertions - https://www.rd-alliance.org/group/fair-digital-object-fabric-ig/outcomes/persistent-identifiers-consolidated-assertions Turning FAIR into reality - Publications Office of the EU [2018, https://data.europa.eu/doi/10.2777/1524]
